{"code":"018700","name":"바른손","market":"KOSDAQ","timeframe":"15m","count":130,"generated":true,"source_days":5,"updated":"2026-03-19T16:50","candles":[{"time":1773360000,"open":604,"high":605,"low":603,"close":604,"volume":77546},{"time":1773360900,"open":604,"high":604,"low":603,"close":603,"volume":47947},{"time":1773361800,"open":603,"high":604,"low":601,"close":602,"volume":35926},{"time":1773362700,"open":602,"high":603,"low":593,"close":594,"volume":33992},{"time":1773363600,"open":594,"high":597,"low":593,"close":597,"volume":40178},{"time":1773364500,"open":597,"high":602,"low":596,"close":602,"volume":111180},{"time":1773365400,"open":602,"high":603,"low":589,"close":590,"volume":67944},{"time":1773366300,"open":590,"high":598,"low":589,"close":598,"volume":68915},{"time":1773367200,"open":598,"high":598,"low":591,"close":591,"volume":135187},{"time":1773368100,"open":591,"high":598,"low":590,"close":598,"volume":56560},{"time":1773369000,"open":598,"high":598,"low":591,"close":591,"volume":57036},{"time":1773369900,"open":591,"high":592,"low":586,"close":586,"volume":121967},{"time":1773370800,"open":586,"high":587,"low":585,"close":585,"volume":67408},{"time":1773371700,"open":585,"high":585,"low":580,"close":580,"volume":137789},{"time":1773372600,"open":580,"high":581,"low":576,"close":577,"volume":64962},{"time":1773373500,"open":577,"high":581,"low":576,"close":581,"volume":72158},{"time":1773374400,"open":581,"high":581,"low":571,"close":571,"volume":98618},{"time":1773375300,"open":571,"high":581,"low":570,"close":580,"volume":133611},{"time":1773376200,"open":580,"high":586,"low":579,"close":586,"volume":83607},{"time":1773377100,"open":586,"high":587,"low":567,"close":568,"volume":103404},{"time":1773378000,"open":568,"high":569,"low":567,"close":567,"volume":63931},{"time":1773378900,"open":567,"high":576,"low":567,"close":575,"volume":92502},{"time":1773379800,"open":575,"high":576,"low":565,"close":565,"volume":87817},{"time":1773380700,"open":565,"high":566,"low":565,"close":566,"volume":55536},{"time":1773381600,"open":566,"high":566,"low":563,"close":563,"volume":69933},{"time":1773382500,"open":563,"high":564,"low":561,"close":562,"volume":58166},{"time":1773619200,"open":562,"high":562,"low":561,"close":562,"volume":21699},{"time":1773620100,"open":562,"high":563,"low":559,"close":560,"volume":22312},{"time":1773621000,"open":560,"high":562,"low":560,"close":562,"volume":15742},{"time":1773621900,"open":562,"high":562,"low":559,"close":559,"volume":21075},{"time":1773622800,"open":559,"high":560,"low":555,"close":556,"volume":16922},{"time":1773623700,"open":556,"high":557,"low":555,"close":556,"volume":20696},{"time":1773624600,"open":556,"high":557,"low":554,"close":555,"volume":28216},{"time":1773625500,"open":555,"high":558,"low":554,"close":558,"volume":47105},{"time":1773626400,"open":558,"high":559,"low":556,"close":556,"volume":27718},{"time":1773627300,"open":556,"high":556,"low":554,"close":554,"volume":26749},{"time":1773628200,"open":554,"high":558,"low":554,"close":557,"volume":43587},{"time":1773629100,"open":557,"high":557,"low":555,"close":556,"volume":43894},{"time":1773630000,"open":556,"high":556,"low":550,"close":551,"volume":28937},{"time":1773630900,"open":551,"high":554,"low":551,"close":553,"volume":45546},{"time":1773631800,"open":553,"high":556,"low":552,"close":555,"volume":37680},{"time":1773632700,"open":555,"high":555,"low":552,"close":552,"volume":36991},{"time":1773633600,"open":552,"high":553,"low":552,"close":553,"volume":46538},{"time":1773634500,"open":553,"high":553,"low":553,"close":553,"volume":31268},{"time":1773635400,"open":553,"high":554,"low":550,"close":550,"volume":37849},{"time":1773636300,"open":550,"high":551,"low":549,"close":550,"volume":46624},{"time":1773637200,"open":550,"high":550,"low":548,"close":548,"volume":38030},{"time":1773638100,"open":548,"high":548,"low":546,"close":547,"volume":29688},{"time":1773639000,"open":547,"high":548,"low":546,"close":547,"volume":33253},{"time":1773639900,"open":547,"high":548,"low":546,"close":547,"volume":21532},{"time":1773640800,"open":547,"high":548,"low":546,"close":546,"volume":34307},{"time":1773641700,"open":546,"high":547,"low":544,"close":545,"volume":31772},{"time":1773705600,"open":550,"high":551,"low":549,"close":550,"volume":12792},{"time":1773706500,"open":550,"high":551,"low":550,"close":550,"volume":11925},{"time":1773707400,"open":550,"high":551,"low":549,"close":550,"volume":7858},{"time":1773708300,"open":550,"high":551,"low":548,"close":549,"volume":10736},{"time":1773709200,"open":549,"high":549,"low":547,"close":548,"volume":7270},{"time":1773710100,"open":548,"high":550,"low":547,"close":550,"volume":17296},{"time":1773711000,"open":550,"high":550,"low":548,"close":549,"volume":19632},{"time":1773711900,"open":549,"high":549,"low":547,"close":548,"volume":9511},{"time":1773712800,"open":548,"high":550,"low":547,"close":550,"volume":17130},{"time":1773713700,"open":550,"high":550,"low":549,"close":549,"volume":16236},{"time":1773714600,"open":549,"high":551,"low":548,"close":550,"volume":15835},{"time":1773715500,"open":550,"high":551,"low":546,"close":546,"volume":16881},{"time":1773716400,"open":546,"high":548,"low":546,"close":547,"volume":20467},{"time":1773717300,"open":547,"high":548,"low":546,"close":547,"volume":22468},{"time":1773718200,"open":547,"high":548,"low":546,"close":546,"volume":10214},{"time":1773719100,"open":546,"high":547,"low":546,"close":547,"volume":18083},{"time":1773720000,"open":547,"high":548,"low":547,"close":548,"volume":11966},{"time":1773720900,"open":548,"high":549,"low":546,"close":547,"volume":16053},{"time":1773721800,"open":547,"high":547,"low":545,"close":546,"volume":21535},{"time":1773722700,"open":546,"high":547,"low":545,"close":547,"volume":8526},{"time":1773723600,"open":547,"high":548,"low":546,"close":547,"volume":6427},{"time":1773724500,"open":547,"high":547,"low":546,"close":547,"volume":7455},{"time":1773725400,"open":547,"high":548,"low":544,"close":545,"volume":5370},{"time":1773726300,"open":545,"high":547,"low":545,"close":546,"volume":12879},{"time":1773727200,"open":546,"high":547,"low":545,"close":545,"volume":9022},{"time":1773728100,"open":545,"high":546,"low":545,"close":545,"volume":7179},{"time":1773792000,"open":541,"high":543,"low":540,"close":542,"volume":18050},{"time":1773792900,"open":542,"high":543,"low":541,"close":542,"volume":22078},{"time":1773793800,"open":542,"high":543,"low":542,"close":542,"volume":20130},{"time":1773794700,"open":542,"high":543,"low":537,"close":537,"volume":11905},{"time":1773795600,"open":537,"high":540,"low":537,"close":540,"volume":27057},{"time":1773796500,"open":540,"high":544,"low":539,"close":543,"volume":23906},{"time":1773797400,"open":543,"high":544,"low":541,"close":542,"volume":35513},{"time":1773798300,"open":542,"high":544,"low":541,"close":544,"volume":18687},{"time":1773799200,"open":544,"high":544,"low":543,"close":543,"volume":35914},{"time":1773800100,"open":543,"high":547,"low":543,"close":546,"volume":47060},{"time":1773801000,"open":546,"high":546,"low":540,"close":541,"volume":54337},{"time":1773801900,"open":541,"high":543,"low":541,"close":543,"volume":42291},{"time":1773802800,"open":543,"high":550,"low":542,"close":550,"volume":48894},{"time":1773803700,"open":550,"high":550,"low":544,"close":545,"volume":50880},{"time":1773804600,"open":545,"high":545,"low":539,"close":540,"volume":27213},{"time":1773805500,"open":540,"high":548,"low":539,"close":548,"volume":51137},{"time":1773806400,"open":548,"high":548,"low":544,"close":545,"volume":47209},{"time":1773807300,"open":545,"high":546,"low":544,"close":545,"volume":18367},{"time":1773808200,"open":545,"high":546,"low":545,"close":545,"volume":40803},{"time":1773809100,"open":545,"high":545,"low":544,"close":545,"volume":39092},{"time":1773810000,"open":545,"high":547,"low":544,"close":546,"volume":32744},{"time":1773810900,"open":546,"high":552,"low":546,"close":552,"volume":26385},{"time":1773811800,"open":552,"high":552,"low":547,"close":548,"volume":27879},{"time":1773812700,"open":548,"high":548,"low":543,"close":544,"volume":14808},{"time":1773813600,"open":544,"high":547,"low":544,"close":546,"volume":25230},{"time":1773814500,"open":546,"high":547,"low":545,"close":547,"volume":26930},{"time":1773878400,"open":547,"high":548,"low":547,"close":548,"volume":2632},{"time":1773879300,"open":548,"high":549,"low":547,"close":548,"volume":4043},{"time":1773880200,"open":548,"high":549,"low":547,"close":548,"volume":2154},{"time":1773881100,"open":548,"high":550,"low":548,"close":549,"volume":5830},{"time":1773882000,"open":549,"high":549,"low":548,"close":549,"volume":2462},{"time":1773882900,"open":549,"high":550,"low":548,"close":550,"volume":3265},{"time":1773883800,"open":550,"high":551,"low":549,"close":549,"volume":3358},{"time":1773884700,"open":549,"high":549,"low":548,"close":549,"volume":5569},{"time":1773885600,"open":549,"high":550,"low":548,"close":550,"volume":8634},{"time":1773886500,"open":550,"high":550,"low":549,"close":550,"volume":6499},{"time":1773887400,"open":550,"high":552,"low":550,"close":551,"volume":4115},{"time":1773888300,"open":551,"high":551,"low":550,"close":551,"volume":8107},{"time":1773889200,"open":551,"high":551,"low":550,"close":551,"volume":7123},{"time":1773890100,"open":551,"high":552,"low":550,"close":552,"volume":7566},{"time":1773891000,"open":552,"high":553,"low":551,"close":552,"volume":4424},{"time":1773891900,"open":552,"high":552,"low":550,"close":551,"volume":7277},{"time":1773892800,"open":551,"high":553,"low":550,"close":552,"volume":5727},{"time":1773893700,"open":552,"high":553,"low":552,"close":552,"volume":4704},{"time":1773894600,"open":552,"high":552,"low":552,"close":552,"volume":4325},{"time":1773895500,"open":552,"high":553,"low":551,"close":553,"volume":2770},{"time":1773896400,"open":553,"high":554,"low":553,"close":554,"volume":5793},{"time":1773897300,"open":554,"high":554,"low":552,"close":553,"volume":4789},{"time":1773898200,"open":553,"high":555,"low":553,"close":554,"volume":4499},{"time":1773899100,"open":554,"high":555,"low":553,"close":554,"volume":2369},{"time":1773900000,"open":554,"high":555,"low":554,"close":555,"volume":4224},{"time":1773900900,"open":555,"high":556,"low":554,"close":555,"volume":2424}]}