{"code":"140430","name":"카티스","market":"KOSDAQ","timeframe":"1m","count":1170,"generated":true,"source_days":3,"updated":"2026-03-19T16:49","candles":[{"time":1773705600,"open":630,"high":631,"low":629,"close":630,"volume":653},{"time":1773705660,"open":630,"high":630,"low":629,"close":630,"volume":383},{"time":1773705720,"open":630,"high":630,"low":630,"close":630,"volume":824},{"time":1773705780,"open":630,"high":630,"low":629,"close":630,"volume":572},{"time":1773705840,"open":630,"high":631,"low":629,"close":630,"volume":728},{"time":1773705900,"open":630,"high":630,"low":629,"close":630,"volume":517},{"time":1773705960,"open":630,"high":630,"low":629,"close":630,"volume":717},{"time":1773706020,"open":630,"high":630,"low":629,"close":630,"volume":733},{"time":1773706080,"open":630,"high":630,"low":629,"close":630,"volume":680},{"time":1773706140,"open":630,"high":630,"low":629,"close":630,"volume":396},{"time":1773706200,"open":630,"high":631,"low":629,"close":630,"volume":562},{"time":1773706260,"open":630,"high":630,"low":630,"close":630,"volume":785},{"time":1773706320,"open":630,"high":632,"low":629,"close":631,"volume":524},{"time":1773706380,"open":631,"high":632,"low":630,"close":631,"volume":376},{"time":1773706440,"open":631,"high":631,"low":629,"close":629,"volume":586},{"time":1773706500,"open":629,"high":631,"low":629,"close":630,"volume":617},{"time":1773706560,"open":630,"high":631,"low":629,"close":630,"volume":635},{"time":1773706620,"open":630,"high":630,"low":628,"close":629,"volume":632},{"time":1773706680,"open":629,"high":630,"low":628,"close":629,"volume":533},{"time":1773706740,"open":629,"high":632,"low":629,"close":631,"volume":369},{"time":1773706800,"open":631,"high":632,"low":628,"close":628,"volume":381},{"time":1773706860,"open":628,"high":630,"low":628,"close":629,"volume":422},{"time":1773706920,"open":629,"high":630,"low":628,"close":630,"volume":507},{"time":1773706980,"open":630,"high":631,"low":629,"close":630,"volume":691},{"time":1773707040,"open":630,"high":632,"low":630,"close":631,"volume":741},{"time":1773707100,"open":631,"high":631,"low":629,"close":630,"volume":844},{"time":1773707160,"open":630,"high":631,"low":628,"close":629,"volume":620},{"time":1773707220,"open":629,"high":629,"low":628,"close":629,"volume":314},{"time":1773707280,"open":629,"high":630,"low":627,"close":628,"volume":746},{"time":1773707340,"open":628,"high":631,"low":628,"close":631,"volume":640},{"time":1773707400,"open":631,"high":631,"low":630,"close":630,"volume":322},{"time":1773707460,"open":630,"high":630,"low":627,"close":628,"volume":397},{"time":1773707520,"open":628,"high":632,"low":627,"close":631,"volume":703},{"time":1773707580,"open":631,"high":632,"low":629,"close":630,"volume":640},{"time":1773707640,"open":630,"high":632,"low":629,"close":631,"volume":698},{"time":1773707700,"open":631,"high":631,"low":628,"close":629,"volume":499},{"time":1773707760,"open":629,"high":630,"low":627,"close":628,"volume":711},{"time":1773707820,"open":628,"high":631,"low":627,"close":630,"volume":679},{"time":1773707880,"open":630,"high":630,"low":628,"close":630,"volume":677},{"time":1773707940,"open":630,"high":631,"low":629,"close":630,"volume":756},{"time":1773708000,"open":630,"high":631,"low":630,"close":631,"volume":602},{"time":1773708060,"open":631,"high":631,"low":627,"close":629,"volume":442},{"time":1773708120,"open":629,"high":631,"low":628,"close":630,"volume":593},{"time":1773708180,"open":630,"high":631,"low":629,"close":629,"volume":573},{"time":1773708240,"open":629,"high":630,"low":627,"close":628,"volume":778},{"time":1773708300,"open":628,"high":631,"low":628,"close":631,"volume":354},{"time":1773708360,"open":631,"high":631,"low":630,"close":630,"volume":890},{"time":1773708420,"open":630,"high":631,"low":629,"close":630,"volume":615},{"time":1773708480,"open":630,"high":630,"low":628,"close":629,"volume":979},{"time":1773708540,"open":629,"high":630,"low":628,"close":630,"volume":766},{"time":1773708600,"open":630,"high":630,"low":629,"close":630,"volume":970},{"time":1773708660,"open":630,"high":630,"low":627,"close":628,"volume":610},{"time":1773708720,"open":628,"high":628,"low":627,"close":628,"volume":428},{"time":1773708780,"open":628,"high":631,"low":627,"close":630,"volume":998},{"time":1773708840,"open":630,"high":631,"low":629,"close":630,"volume":427},{"time":1773708900,"open":630,"high":631,"low":628,"close":629,"volume":860},{"time":1773708960,"open":629,"high":631,"low":628,"close":630,"volume":443},{"time":1773709020,"open":630,"high":631,"low":628,"close":629,"volume":514},{"time":1773709080,"open":629,"high":630,"low":627,"close":629,"volume":1029},{"time":1773709140,"open":629,"high":631,"low":628,"close":630,"volume":1010},{"time":1773709200,"open":630,"high":632,"low":629,"close":631,"volume":795},{"time":1773709260,"open":631,"high":632,"low":629,"close":630,"volume":923},{"time":1773709320,"open":630,"high":631,"low":630,"close":630,"volume":676},{"time":1773709380,"open":630,"high":631,"low":630,"close":630,"volume":765},{"time":1773709440,"open":630,"high":632,"low":630,"close":631,"volume":608},{"time":1773709500,"open":631,"high":632,"low":628,"close":628,"volume":935},{"time":1773709560,"open":628,"high":631,"low":627,"close":630,"volume":552},{"time":1773709620,"open":630,"high":631,"low":629,"close":630,"volume":1046},{"time":1773709680,"open":630,"high":631,"low":629,"close":630,"volume":991},{"time":1773709740,"open":630,"high":631,"low":627,"close":628,"volume":744},{"time":1773709800,"open":628,"high":631,"low":628,"close":630,"volume":748},{"time":1773709860,"open":630,"high":630,"low":628,"close":629,"volume":919},{"time":1773709920,"open":629,"high":630,"low":628,"close":628,"volume":942},{"time":1773709980,"open":628,"high":629,"low":627,"close":629,"volume":435},{"time":1773710040,"open":629,"high":632,"low":628,"close":630,"volume":814},{"time":1773710100,"open":630,"high":631,"low":629,"close":630,"volume":989},{"time":1773710160,"open":630,"high":631,"low":628,"close":628,"volume":869},{"time":1773710220,"open":628,"high":630,"low":627,"close":629,"volume":619},{"time":1773710280,"open":629,"high":631,"low":628,"close":631,"volume":524},{"time":1773710340,"open":631,"high":631,"low":629,"close":629,"volume":577},{"time":1773710400,"open":629,"high":630,"low":629,"close":629,"volume":443},{"time":1773710460,"open":629,"high":630,"low":629,"close":629,"volume":1168},{"time":1773710520,"open":629,"high":630,"low":628,"close":630,"volume":805},{"time":1773710580,"open":630,"high":630,"low":629,"close":630,"volume":817},{"time":1773710640,"open":630,"high":630,"low":629,"close":629,"volume":1039},{"time":1773710700,"open":629,"high":630,"low":628,"close":629,"volume":479},{"time":1773710760,"open":629,"high":630,"low":629,"close":629,"volume":414},{"time":1773710820,"open":629,"high":630,"low":627,"close":628,"volume":933},{"time":1773710880,"open":628,"high":629,"low":627,"close":628,"volume":1198},{"time":1773710940,"open":628,"high":631,"low":627,"close":630,"volume":426},{"time":1773711000,"open":630,"high":631,"low":627,"close":628,"volume":869},{"time":1773711060,"open":628,"high":630,"low":628,"close":629,"volume":951},{"time":1773711120,"open":629,"high":630,"low":627,"close":627,"volume":455},{"time":1773711180,"open":627,"high":629,"low":626,"close":629,"volume":454},{"time":1773711240,"open":629,"high":629,"low":627,"close":629,"volume":606},{"time":1773711300,"open":629,"high":631,"low":627,"close":631,"volume":532},{"time":1773711360,"open":631,"high":631,"low":629,"close":630,"volume":1008},{"time":1773711420,"open":630,"high":630,"low":629,"close":630,"volume":777},{"time":1773711480,"open":630,"high":631,"low":628,"close":628,"volume":1247},{"time":1773711540,"open":628,"high":631,"low":627,"close":630,"volume":608},{"time":1773711600,"open":630,"high":630,"low":627,"close":628,"volume":821},{"time":1773711660,"open":628,"high":631,"low":628,"close":630,"volume":918},{"time":1773711720,"open":630,"high":632,"low":627,"close":628,"volume":895},{"time":1773711780,"open":628,"high":629,"low":626,"close":627,"volume":887},{"time":1773711840,"open":627,"high":629,"low":627,"close":629,"volume":930},{"time":1773711900,"open":629,"high":630,"low":628,"close":629,"volume":548},{"time":1773711960,"open":629,"high":630,"low":629,"close":629,"volume":962},{"time":1773712020,"open":629,"high":630,"low":629,"close":630,"volume":719},{"time":1773712080,"open":630,"high":631,"low":629,"close":630,"volume":565},{"time":1773712140,"open":630,"high":630,"low":626,"close":626,"volume":1228},{"time":1773712200,"open":626,"high":630,"low":626,"close":630,"volume":868},{"time":1773712260,"open":630,"high":632,"low":629,"close":631,"volume":604},{"time":1773712320,"open":631,"high":631,"low":629,"close":630,"volume":1342},{"time":1773712380,"open":630,"high":631,"low":627,"close":627,"volume":480},{"time":1773712440,"open":627,"high":628,"low":627,"close":628,"volume":1152},{"time":1773712500,"open":628,"high":629,"low":627,"close":628,"volume":798},{"time":1773712560,"open":628,"high":629,"low":628,"close":628,"volume":771},{"time":1773712620,"open":628,"high":628,"low":627,"close":628,"volume":496},{"time":1773712680,"open":628,"high":629,"low":627,"close":628,"volume":589},{"time":1773712740,"open":628,"high":631,"low":626,"close":631,"volume":1397},{"time":1773712800,"open":631,"high":632,"low":629,"close":629,"volume":780},{"time":1773712860,"open":629,"high":632,"low":629,"close":632,"volume":980},{"time":1773712920,"open":632,"high":633,"low":628,"close":628,"volume":1006},{"time":1773712980,"open":628,"high":630,"low":628,"close":629,"volume":918},{"time":1773713040,"open":629,"high":630,"low":627,"close":628,"volume":1115},{"time":1773713100,"open":628,"high":629,"low":627,"close":628,"volume":1024},{"time":1773713160,"open":628,"high":628,"low":627,"close":627,"volume":577},{"time":1773713220,"open":627,"high":630,"low":627,"close":630,"volume":535},{"time":1773713280,"open":630,"high":630,"low":629,"close":629,"volume":817},{"time":1773713340,"open":629,"high":630,"low":628,"close":630,"volume":1413},{"time":1773713400,"open":630,"high":630,"low":627,"close":627,"volume":636},{"time":1773713460,"open":627,"high":628,"low":625,"close":626,"volume":1212},{"time":1773713520,"open":626,"high":630,"low":625,"close":629,"volume":889},{"time":1773713580,"open":629,"high":630,"low":628,"close":629,"volume":837},{"time":1773713640,"open":629,"high":630,"low":628,"close":629,"volume":594},{"time":1773713700,"open":629,"high":630,"low":628,"close":629,"volume":1202},{"time":1773713760,"open":629,"high":632,"low":628,"close":631,"volume":520},{"time":1773713820,"open":631,"high":631,"low":628,"close":629,"volume":807},{"time":1773713880,"open":629,"high":630,"low":627,"close":627,"volume":829},{"time":1773713940,"open":627,"high":630,"low":627,"close":629,"volume":1235},{"time":1773714000,"open":629,"high":629,"low":627,"close":628,"volume":773},{"time":1773714060,"open":628,"high":630,"low":626,"close":630,"volume":1182},{"time":1773714120,"open":630,"high":630,"low":626,"close":627,"volume":1448},{"time":1773714180,"open":627,"high":631,"low":627,"close":631,"volume":978},{"time":1773714240,"open":631,"high":632,"low":628,"close":630,"volume":1102},{"time":1773714300,"open":630,"high":630,"low":629,"close":629,"volume":1268},{"time":1773714360,"open":629,"high":630,"low":627,"close":628,"volume":1200},{"time":1773714420,"open":628,"high":629,"low":627,"close":629,"volume":780},{"time":1773714480,"open":629,"high":630,"low":626,"close":628,"volume":1478},{"time":1773714540,"open":628,"high":630,"low":627,"close":629,"volume":915},{"time":1773714600,"open":629,"high":629,"low":628,"close":628,"volume":647},{"time":1773714660,"open":628,"high":629,"low":627,"close":628,"volume":1094},{"time":1773714720,"open":628,"high":630,"low":628,"close":629,"volume":944},{"time":1773714780,"open":629,"high":630,"low":628,"close":629,"volume":781},{"time":1773714840,"open":629,"high":631,"low":628,"close":630,"volume":763},{"time":1773714900,"open":630,"high":630,"low":629,"close":629,"volume":1002},{"time":1773714960,"open":629,"high":630,"low":629,"close":629,"volume":658},{"time":1773715020,"open":629,"high":632,"low":629,"close":631,"volume":977},{"time":1773715080,"open":631,"high":632,"low":627,"close":628,"volume":665},{"time":1773715140,"open":628,"high":629,"low":627,"close":628,"volume":887},{"time":1773715200,"open":628,"high":629,"low":626,"close":626,"volume":1486},{"time":1773715260,"open":626,"high":632,"low":626,"close":632,"volume":1266},{"time":1773715320,"open":632,"high":633,"low":628,"close":629,"volume":1394},{"time":1773715380,"open":629,"high":630,"low":624,"close":625,"volume":662},{"time":1773715440,"open":625,"high":630,"low":625,"close":629,"volume":879},{"time":1773715500,"open":629,"high":630,"low":628,"close":629,"volume":937},{"time":1773715560,"open":629,"high":630,"low":628,"close":630,"volume":632},{"time":1773715620,"open":630,"high":631,"low":630,"close":630,"volume":1362},{"time":1773715680,"open":630,"high":631,"low":628,"close":629,"volume":774},{"time":1773715740,"open":629,"high":630,"low":627,"close":628,"volume":676},{"time":1773715800,"open":628,"high":631,"low":627,"close":630,"volume":1247},{"time":1773715860,"open":630,"high":631,"low":628,"close":629,"volume":1283},{"time":1773715920,"open":629,"high":630,"low":627,"close":628,"volume":660},{"time":1773715980,"open":628,"high":630,"low":627,"close":630,"volume":1255},{"time":1773716040,"open":630,"high":630,"low":624,"close":625,"volume":821},{"time":1773716100,"open":625,"high":630,"low":624,"close":630,"volume":607},{"time":1773716160,"open":630,"high":631,"low":628,"close":628,"volume":1610},{"time":1773716220,"open":628,"high":631,"low":628,"close":631,"volume":633},{"time":1773716280,"open":631,"high":631,"low":628,"close":629,"volume":1410},{"time":1773716340,"open":629,"high":631,"low":629,"close":630,"volume":953},{"time":1773716400,"open":630,"high":630,"low":627,"close":628,"volume":893},{"time":1773716460,"open":628,"high":629,"low":627,"close":628,"volume":1167},{"time":1773716520,"open":628,"high":631,"low":628,"close":630,"volume":647},{"time":1773716580,"open":630,"high":631,"low":627,"close":627,"volume":1582},{"time":1773716640,"open":627,"high":628,"low":624,"close":625,"volume":1434},{"time":1773716700,"open":625,"high":626,"low":624,"close":626,"volume":1676},{"time":1773716760,"open":626,"high":628,"low":625,"close":628,"volume":1599},{"time":1773716820,"open":628,"high":629,"low":627,"close":628,"volume":1291},{"time":1773716880,"open":628,"high":628,"low":627,"close":627,"volume":882},{"time":1773716940,"open":627,"high":629,"low":627,"close":629,"volume":865},{"time":1773717000,"open":629,"high":632,"low":629,"close":632,"volume":930},{"time":1773717060,"open":632,"high":632,"low":628,"close":628,"volume":806},{"time":1773717120,"open":628,"high":628,"low":627,"close":627,"volume":1188},{"time":1773717180,"open":627,"high":628,"low":625,"close":625,"volume":1541},{"time":1773717240,"open":625,"high":628,"low":625,"close":627,"volume":902},{"time":1773717300,"open":627,"high":629,"low":626,"close":628,"volume":786},{"time":1773717360,"open":628,"high":631,"low":627,"close":631,"volume":701},{"time":1773717420,"open":631,"high":632,"low":626,"close":628,"volume":742},{"time":1773717480,"open":628,"high":631,"low":627,"close":630,"volume":1033},{"time":1773717540,"open":630,"high":631,"low":626,"close":627,"volume":867},{"time":1773717600,"open":627,"high":628,"low":625,"close":626,"volume":1201},{"time":1773717660,"open":626,"high":630,"low":626,"close":629,"volume":1254},{"time":1773717720,"open":629,"high":631,"low":628,"close":631,"volume":1510},{"time":1773717780,"open":631,"high":632,"low":629,"close":630,"volume":1411},{"time":1773717840,"open":630,"high":631,"low":627,"close":629,"volume":711},{"time":1773717900,"open":629,"high":629,"low":626,"close":627,"volume":698},{"time":1773717960,"open":627,"high":627,"low":626,"close":627,"volume":821},{"time":1773718020,"open":627,"high":628,"low":626,"close":627,"volume":1623},{"time":1773718080,"open":627,"high":627,"low":626,"close":626,"volume":1643},{"time":1773718140,"open":626,"high":630,"low":626,"close":629,"volume":1433},{"time":1773718200,"open":629,"high":630,"low":626,"close":627,"volume":838},{"time":1773718260,"open":627,"high":630,"low":626,"close":629,"volume":1559},{"time":1773718320,"open":629,"high":631,"low":628,"close":631,"volume":1464},{"time":1773718380,"open":631,"high":631,"low":626,"close":626,"volume":1181},{"time":1773718440,"open":626,"high":629,"low":625,"close":628,"volume":956},{"time":1773718500,"open":628,"high":629,"low":624,"close":625,"volume":943},{"time":1773718560,"open":625,"high":628,"low":625,"close":628,"volume":985},{"time":1773718620,"open":628,"high":631,"low":627,"close":630,"volume":1319},{"time":1773718680,"open":630,"high":631,"low":624,"close":625,"volume":1506},{"time":1773718740,"open":625,"high":626,"low":624,"close":625,"volume":1437},{"time":1773718800,"open":625,"high":631,"low":625,"close":630,"volume":1558},{"time":1773718860,"open":630,"high":631,"low":628,"close":628,"volume":1002},{"time":1773718920,"open":628,"high":630,"low":626,"close":627,"volume":647},{"time":1773718980,"open":627,"high":627,"low":625,"close":626,"volume":712},{"time":1773719040,"open":626,"high":627,"low":625,"close":626,"volume":952},{"time":1773719100,"open":626,"high":628,"low":626,"close":628,"volume":1068},{"time":1773719160,"open":628,"high":629,"low":627,"close":628,"volume":894},{"time":1773719220,"open":628,"high":629,"low":626,"close":626,"volume":1579},{"time":1773719280,"open":626,"high":628,"low":626,"close":627,"volume":1190},{"time":1773719340,"open":627,"high":628,"low":625,"close":626,"volume":1564},{"time":1773719400,"open":626,"high":630,"low":626,"close":629,"volume":1567},{"time":1773719460,"open":629,"high":630,"low":625,"close":627,"volume":977},{"time":1773719520,"open":627,"high":630,"low":626,"close":629,"volume":1511},{"time":1773719580,"open":629,"high":629,"low":627,"close":627,"volume":661},{"time":1773719640,"open":627,"high":630,"low":625,"close":629,"volume":1222},{"time":1773719700,"open":629,"high":629,"low":626,"close":626,"volume":1417},{"time":1773719760,"open":626,"high":631,"low":626,"close":630,"volume":1415},{"time":1773719820,"open":630,"high":631,"low":626,"close":627,"volume":1098},{"time":1773719880,"open":627,"high":629,"low":626,"close":629,"volume":986},{"time":1773719940,"open":629,"high":630,"low":628,"close":629,"volume":674},{"time":1773720000,"open":629,"high":629,"low":626,"close":627,"volume":653},{"time":1773720060,"open":627,"high":629,"low":627,"close":628,"volume":1595},{"time":1773720120,"open":628,"high":629,"low":627,"close":627,"volume":1153},{"time":1773720180,"open":627,"high":629,"low":627,"close":628,"volume":736},{"time":1773720240,"open":628,"high":629,"low":627,"close":628,"volume":889},{"time":1773720300,"open":628,"high":629,"low":627,"close":627,"volume":1509},{"time":1773720360,"open":627,"high":630,"low":627,"close":629,"volume":555},{"time":1773720420,"open":629,"high":630,"low":625,"close":626,"volume":752},{"time":1773720480,"open":626,"high":627,"low":625,"close":627,"volume":997},{"time":1773720540,"open":627,"high":629,"low":627,"close":629,"volume":565},{"time":1773720600,"open":629,"high":630,"low":627,"close":628,"volume":908},{"time":1773720660,"open":628,"high":628,"low":625,"close":626,"volume":924},{"time":1773720720,"open":626,"high":629,"low":626,"close":628,"volume":938},{"time":1773720780,"open":628,"high":630,"low":627,"close":629,"volume":1505},{"time":1773720840,"open":629,"high":630,"low":627,"close":627,"volume":801},{"time":1773720900,"open":627,"high":628,"low":626,"close":627,"volume":557},{"time":1773720960,"open":627,"high":627,"low":626,"close":627,"volume":726},{"time":1773721020,"open":627,"high":627,"low":627,"close":627,"volume":611},{"time":1773721080,"open":627,"high":627,"low":624,"close":625,"volume":560},{"time":1773721140,"open":625,"high":628,"low":624,"close":627,"volume":1111},{"time":1773721200,"open":627,"high":628,"low":626,"close":628,"volume":1118},{"time":1773721260,"open":628,"high":628,"low":625,"close":626,"volume":1093},{"time":1773721320,"open":626,"high":628,"low":625,"close":628,"volume":846},{"time":1773721380,"open":628,"high":628,"low":625,"close":626,"volume":989},{"time":1773721440,"open":626,"high":627,"low":626,"close":626,"volume":922},{"time":1773721500,"open":626,"high":629,"low":625,"close":628,"volume":1205},{"time":1773721560,"open":628,"high":629,"low":625,"close":626,"volume":1289},{"time":1773721620,"open":626,"high":629,"low":625,"close":628,"volume":560},{"time":1773721680,"open":628,"high":630,"low":627,"close":630,"volume":1272},{"time":1773721740,"open":630,"high":630,"low":626,"close":626,"volume":649},{"time":1773721800,"open":626,"high":628,"low":626,"close":627,"volume":928},{"time":1773721860,"open":627,"high":629,"low":627,"close":628,"volume":738},{"time":1773721920,"open":628,"high":628,"low":626,"close":627,"volume":866},{"time":1773721980,"open":627,"high":628,"low":627,"close":627,"volume":1003},{"time":1773722040,"open":627,"high":628,"low":625,"close":625,"volume":693},{"time":1773722100,"open":625,"high":627,"low":625,"close":627,"volume":478},{"time":1773722160,"open":627,"high":630,"low":626,"close":629,"volume":1123},{"time":1773722220,"open":629,"high":629,"low":626,"close":626,"volume":537},{"time":1773722280,"open":626,"high":628,"low":625,"close":628,"volume":821},{"time":1773722340,"open":628,"high":628,"low":625,"close":625,"volume":1072},{"time":1773722400,"open":625,"high":627,"low":624,"close":626,"volume":971},{"time":1773722460,"open":626,"high":629,"low":625,"close":628,"volume":1067},{"time":1773722520,"open":628,"high":628,"low":626,"close":627,"volume":779},{"time":1773722580,"open":627,"high":628,"low":626,"close":627,"volume":537},{"time":1773722640,"open":627,"high":627,"low":627,"close":627,"volume":995},{"time":1773722700,"open":627,"high":628,"low":626,"close":626,"volume":956},{"time":1773722760,"open":626,"high":627,"low":625,"close":626,"volume":1019},{"time":1773722820,"open":626,"high":628,"low":625,"close":628,"volume":612},{"time":1773722880,"open":628,"high":628,"low":627,"close":628,"volume":923},{"time":1773722940,"open":628,"high":628,"low":627,"close":628,"volume":1242},{"time":1773723000,"open":628,"high":628,"low":624,"close":625,"volume":1300},{"time":1773723060,"open":625,"high":625,"low":624,"close":624,"volume":539},{"time":1773723120,"open":624,"high":629,"low":624,"close":628,"volume":632},{"time":1773723180,"open":628,"high":628,"low":627,"close":628,"volume":913},{"time":1773723240,"open":628,"high":629,"low":625,"close":626,"volume":969},{"time":1773723300,"open":626,"high":628,"low":625,"close":627,"volume":1255},{"time":1773723360,"open":627,"high":629,"low":626,"close":628,"volume":692},{"time":1773723420,"open":628,"high":630,"low":627,"close":629,"volume":550},{"time":1773723480,"open":629,"high":630,"low":625,"close":626,"volume":766},{"time":1773723540,"open":626,"high":626,"low":625,"close":626,"volume":743},{"time":1773723600,"open":626,"high":626,"low":625,"close":626,"volume":412},{"time":1773723660,"open":626,"high":627,"low":625,"close":627,"volume":860},{"time":1773723720,"open":627,"high":627,"low":626,"close":626,"volume":1132},{"time":1773723780,"open":626,"high":628,"low":626,"close":628,"volume":690},{"time":1773723840,"open":628,"high":630,"low":627,"close":629,"volume":973},{"time":1773723900,"open":629,"high":630,"low":628,"close":628,"volume":1117},{"time":1773723960,"open":628,"high":629,"low":628,"close":628,"volume":1060},{"time":1773724020,"open":628,"high":629,"low":627,"close":627,"volume":1126},{"time":1773724080,"open":627,"high":628,"low":626,"close":627,"volume":1109},{"time":1773724140,"open":627,"high":628,"low":625,"close":625,"volume":410},{"time":1773724200,"open":625,"high":628,"low":624,"close":627,"volume":608},{"time":1773724260,"open":627,"high":629,"low":626,"close":628,"volume":931},{"time":1773724320,"open":628,"high":629,"low":626,"close":627,"volume":517},{"time":1773724380,"open":627,"high":627,"low":624,"close":625,"volume":678},{"time":1773724440,"open":625,"high":627,"low":625,"close":626,"volume":492},{"time":1773724500,"open":626,"high":626,"low":625,"close":626,"volume":626},{"time":1773724560,"open":626,"high":627,"low":625,"close":626,"volume":912},{"time":1773724620,"open":626,"high":631,"low":625,"close":630,"volume":380},{"time":1773724680,"open":630,"high":630,"low":624,"close":625,"volume":595},{"time":1773724740,"open":625,"high":629,"low":624,"close":628,"volume":1067},{"time":1773724800,"open":628,"high":629,"low":626,"close":627,"volume":607},{"time":1773724860,"open":627,"high":628,"low":625,"close":627,"volume":870},{"time":1773724920,"open":627,"high":628,"low":626,"close":628,"volume":1028},{"time":1773724980,"open":628,"high":630,"low":626,"close":626,"volume":917},{"time":1773725040,"open":626,"high":628,"low":626,"close":627,"volume":759},{"time":1773725100,"open":627,"high":628,"low":627,"close":628,"volume":786},{"time":1773725160,"open":628,"high":629,"low":626,"close":627,"volume":764},{"time":1773725220,"open":627,"high":628,"low":625,"close":626,"volume":559},{"time":1773725280,"open":626,"high":628,"low":625,"close":627,"volume":516},{"time":1773725340,"open":627,"high":628,"low":626,"close":627,"volume":595},{"time":1773725400,"open":627,"high":628,"low":626,"close":628,"volume":663},{"time":1773725460,"open":628,"high":629,"low":626,"close":627,"volume":1015},{"time":1773725520,"open":627,"high":627,"low":625,"close":627,"volume":446},{"time":1773725580,"open":627,"high":627,"low":627,"close":627,"volume":659},{"time":1773725640,"open":627,"high":628,"low":626,"close":627,"volume":853},{"time":1773725700,"open":627,"high":628,"low":624,"close":625,"volume":810},{"time":1773725760,"open":625,"high":630,"low":624,"close":629,"volume":573},{"time":1773725820,"open":629,"high":629,"low":625,"close":627,"volume":937},{"time":1773725880,"open":627,"high":628,"low":625,"close":626,"volume":353},{"time":1773725940,"open":626,"high":627,"low":625,"close":626,"volume":973},{"time":1773726000,"open":626,"high":629,"low":626,"close":628,"volume":342},{"time":1773726060,"open":628,"high":629,"low":625,"close":626,"volume":476},{"time":1773726120,"open":626,"high":627,"low":625,"close":625,"volume":567},{"time":1773726180,"open":625,"high":628,"low":625,"close":628,"volume":473},{"time":1773726240,"open":628,"high":628,"low":625,"close":626,"volume":610},{"time":1773726300,"open":626,"high":627,"low":625,"close":626,"volume":542},{"time":1773726360,"open":626,"high":626,"low":625,"close":626,"volume":389},{"time":1773726420,"open":626,"high":628,"low":625,"close":627,"volume":607},{"time":1773726480,"open":627,"high":629,"low":626,"close":628,"volume":771},{"time":1773726540,"open":628,"high":629,"low":625,"close":625,"volume":483},{"time":1773726600,"open":625,"high":627,"low":624,"close":627,"volume":321},{"time":1773726660,"open":627,"high":627,"low":625,"close":626,"volume":901},{"time":1773726720,"open":626,"high":627,"low":625,"close":626,"volume":926},{"time":1773726780,"open":626,"high":627,"low":626,"close":627,"volume":909},{"time":1773726840,"open":627,"high":628,"low":624,"close":625,"volume":596},{"time":1773726900,"open":625,"high":626,"low":624,"close":625,"volume":825},{"time":1773726960,"open":625,"high":626,"low":623,"close":626,"volume":744},{"time":1773727020,"open":626,"high":627,"low":625,"close":625,"volume":344},{"time":1773727080,"open":625,"high":627,"low":625,"close":626,"volume":601},{"time":1773727140,"open":626,"high":628,"low":626,"close":627,"volume":303},{"time":1773727200,"open":627,"high":628,"low":625,"close":626,"volume":699},{"time":1773727260,"open":626,"high":627,"low":625,"close":626,"volume":742},{"time":1773727320,"open":626,"high":627,"low":626,"close":627,"volume":453},{"time":1773727380,"open":627,"high":627,"low":625,"close":625,"volume":851},{"time":1773727440,"open":625,"high":626,"low":625,"close":626,"volume":839},{"time":1773727500,"open":626,"high":628,"low":625,"close":627,"volume":500},{"time":1773727560,"open":627,"high":628,"low":626,"close":627,"volume":306},{"time":1773727620,"open":627,"high":627,"low":625,"close":625,"volume":767},{"time":1773727680,"open":625,"high":626,"low":624,"close":626,"volume":863},{"time":1773727740,"open":626,"high":626,"low":626,"close":626,"volume":751},{"time":1773727800,"open":626,"high":627,"low":626,"close":627,"volume":307},{"time":1773727860,"open":627,"high":627,"low":625,"close":626,"volume":833},{"time":1773727920,"open":626,"high":626,"low":625,"close":626,"volume":792},{"time":1773727980,"open":626,"high":627,"low":625,"close":626,"volume":763},{"time":1773728040,"open":626,"high":627,"low":625,"close":626,"volume":403},{"time":1773728100,"open":626,"high":628,"low":625,"close":627,"volume":437},{"time":1773728160,"open":627,"high":628,"low":625,"close":626,"volume":476},{"time":1773728220,"open":626,"high":627,"low":625,"close":626,"volume":359},{"time":1773728280,"open":626,"high":626,"low":625,"close":626,"volume":774},{"time":1773728340,"open":626,"high":627,"low":626,"close":626,"volume":605},{"time":1773728400,"open":626,"high":628,"low":626,"close":627,"volume":743},{"time":1773728460,"open":627,"high":628,"low":625,"close":627,"volume":744},{"time":1773728520,"open":627,"high":627,"low":625,"close":626,"volume":668},{"time":1773728580,"open":626,"high":626,"low":625,"close":625,"volume":303},{"time":1773728640,"open":625,"high":627,"low":625,"close":627,"volume":503},{"time":1773728700,"open":627,"high":628,"low":626,"close":626,"volume":556},{"time":1773728760,"open":626,"high":626,"low":626,"close":626,"volume":718},{"time":1773728820,"open":626,"high":627,"low":625,"close":626,"volume":808},{"time":1773728880,"open":626,"high":627,"low":625,"close":626,"volume":624},{"time":1773728940,"open":626,"high":627,"low":625,"close":626,"volume":621},{"time":1773792000,"open":626,"high":627,"low":626,"close":626,"volume":5640},{"time":1773792060,"open":626,"high":627,"low":626,"close":626,"volume":4692},{"time":1773792120,"open":626,"high":627,"low":626,"close":626,"volume":2682},{"time":1773792180,"open":626,"high":628,"low":626,"close":627,"volume":4689},{"time":1773792240,"open":627,"high":628,"low":626,"close":626,"volume":4461},{"time":1773792300,"open":626,"high":628,"low":626,"close":627,"volume":2342},{"time":1773792360,"open":627,"high":628,"low":626,"close":626,"volume":3120},{"time":1773792420,"open":626,"high":627,"low":626,"close":626,"volume":6494},{"time":1773792480,"open":626,"high":628,"low":626,"close":627,"volume":6198},{"time":1773792540,"open":627,"high":628,"low":626,"close":626,"volume":2791},{"time":1773792600,"open":626,"high":627,"low":626,"close":626,"volume":3392},{"time":1773792660,"open":626,"high":626,"low":626,"close":626,"volume":2689},{"time":1773792720,"open":626,"high":627,"low":626,"close":626,"volume":2983},{"time":1773792780,"open":626,"high":626,"low":626,"close":626,"volume":2358},{"time":1773792840,"open":626,"high":627,"low":626,"close":626,"volume":5478},{"time":1773792900,"open":626,"high":627,"low":626,"close":626,"volume":5365},{"time":1773792960,"open":626,"high":629,"low":626,"close":628,"volume":5165},{"time":1773793020,"open":628,"high":628,"low":626,"close":626,"volume":5789},{"time":1773793080,"open":626,"high":627,"low":626,"close":626,"volume":3145},{"time":1773793140,"open":626,"high":628,"low":626,"close":627,"volume":6367},{"time":1773793200,"open":627,"high":627,"low":626,"close":626,"volume":4948},{"time":1773793260,"open":626,"high":627,"low":626,"close":626,"volume":6614},{"time":1773793320,"open":626,"high":631,"low":626,"close":630,"volume":5726},{"time":1773793380,"open":630,"high":630,"low":626,"close":626,"volume":4715},{"time":1773793440,"open":626,"high":630,"low":626,"close":629,"volume":4481},{"time":1773793500,"open":629,"high":630,"low":626,"close":627,"volume":6760},{"time":1773793560,"open":627,"high":628,"low":626,"close":626,"volume":3531},{"time":1773793620,"open":626,"high":628,"low":626,"close":627,"volume":4944},{"time":1773793680,"open":627,"high":629,"low":626,"close":628,"volume":5328},{"time":1773793740,"open":628,"high":629,"low":626,"close":626,"volume":6391},{"time":1773793800,"open":626,"high":626,"low":626,"close":626,"volume":5086},{"time":1773793860,"open":626,"high":627,"low":626,"close":626,"volume":6254},{"time":1773793920,"open":626,"high":627,"low":626,"close":626,"volume":4978},{"time":1773793980,"open":626,"high":627,"low":626,"close":626,"volume":2779},{"time":1773794040,"open":626,"high":627,"low":626,"close":627,"volume":7393},{"time":1773794100,"open":627,"high":627,"low":626,"close":626,"volume":6638},{"time":1773794160,"open":626,"high":627,"low":626,"close":626,"volume":7237},{"time":1773794220,"open":626,"high":630,"low":626,"close":630,"volume":4701},{"time":1773794280,"open":630,"high":630,"low":626,"close":627,"volume":6782},{"time":1773794340,"open":627,"high":629,"low":626,"close":628,"volume":7503},{"time":1773794400,"open":628,"high":633,"low":627,"close":632,"volume":6880},{"time":1773794460,"open":632,"high":634,"low":626,"close":626,"volume":2689},{"time":1773794520,"open":626,"high":628,"low":626,"close":628,"volume":4758},{"time":1773794580,"open":628,"high":628,"low":626,"close":626,"volume":7052},{"time":1773794640,"open":626,"high":627,"low":626,"close":627,"volume":6855},{"time":1773794700,"open":627,"high":627,"low":626,"close":627,"volume":5975},{"time":1773794760,"open":627,"high":628,"low":626,"close":628,"volume":3253},{"time":1773794820,"open":628,"high":631,"low":627,"close":631,"volume":6557},{"time":1773794880,"open":631,"high":631,"low":626,"close":626,"volume":4821},{"time":1773794940,"open":626,"high":627,"low":626,"close":627,"volume":7318},{"time":1773795000,"open":627,"high":629,"low":627,"close":628,"volume":6835},{"time":1773795060,"open":628,"high":633,"low":628,"close":632,"volume":2890},{"time":1773795120,"open":632,"high":633,"low":628,"close":628,"volume":5044},{"time":1773795180,"open":628,"high":628,"low":626,"close":626,"volume":5997},{"time":1773795240,"open":626,"high":632,"low":626,"close":631,"volume":7564},{"time":1773795300,"open":631,"high":632,"low":629,"close":629,"volume":7441},{"time":1773795360,"open":629,"high":630,"low":628,"close":629,"volume":3485},{"time":1773795420,"open":629,"high":631,"low":627,"close":627,"volume":4705},{"time":1773795480,"open":627,"high":629,"low":627,"close":628,"volume":7616},{"time":1773795540,"open":628,"high":629,"low":626,"close":626,"volume":3949},{"time":1773795600,"open":626,"high":627,"low":626,"close":626,"volume":8105},{"time":1773795660,"open":626,"high":630,"low":626,"close":630,"volume":6478},{"time":1773795720,"open":630,"high":630,"low":626,"close":626,"volume":8256},{"time":1773795780,"open":626,"high":627,"low":626,"close":626,"volume":4176},{"time":1773795840,"open":626,"high":627,"low":626,"close":626,"volume":8445},{"time":1773795900,"open":626,"high":627,"low":626,"close":626,"volume":5677},{"time":1773795960,"open":626,"high":626,"low":626,"close":626,"volume":3708},{"time":1773796020,"open":626,"high":627,"low":626,"close":627,"volume":8364},{"time":1773796080,"open":627,"high":630,"low":627,"close":630,"volume":4517},{"time":1773796140,"open":630,"high":630,"low":627,"close":627,"volume":5366},{"time":1773796200,"open":627,"high":628,"low":626,"close":626,"volume":8028},{"time":1773796260,"open":626,"high":627,"low":626,"close":626,"volume":8637},{"time":1773796320,"open":626,"high":626,"low":626,"close":626,"volume":4870},{"time":1773796380,"open":626,"high":628,"low":626,"close":627,"volume":6514},{"time":1773796440,"open":627,"high":630,"low":626,"close":629,"volume":6776},{"time":1773796500,"open":629,"high":631,"low":628,"close":630,"volume":7345},{"time":1773796560,"open":630,"high":631,"low":626,"close":626,"volume":6628},{"time":1773796620,"open":626,"high":629,"low":626,"close":629,"volume":8767},{"time":1773796680,"open":629,"high":629,"low":626,"close":626,"volume":4215},{"time":1773796740,"open":626,"high":627,"low":626,"close":626,"volume":5191},{"time":1773796800,"open":626,"high":629,"low":626,"close":628,"volume":5686},{"time":1773796860,"open":628,"high":629,"low":627,"close":628,"volume":6029},{"time":1773796920,"open":628,"high":629,"low":627,"close":628,"volume":6278},{"time":1773796980,"open":628,"high":633,"low":627,"close":633,"volume":5976},{"time":1773797040,"open":633,"high":634,"low":629,"close":629,"volume":5980},{"time":1773797100,"open":629,"high":630,"low":626,"close":626,"volume":6811},{"time":1773797160,"open":626,"high":627,"low":626,"close":626,"volume":9410},{"time":1773797220,"open":626,"high":629,"low":626,"close":628,"volume":8456},{"time":1773797280,"open":628,"high":629,"low":627,"close":628,"volume":5872},{"time":1773797340,"open":628,"high":630,"low":628,"close":630,"volume":5271},{"time":1773797400,"open":630,"high":630,"low":627,"close":627,"volume":3776},{"time":1773797460,"open":627,"high":633,"low":626,"close":633,"volume":3493},{"time":1773797520,"open":633,"high":633,"low":627,"close":627,"volume":4336},{"time":1773797580,"open":627,"high":631,"low":627,"close":630,"volume":4307},{"time":1773797640,"open":630,"high":631,"low":626,"close":626,"volume":4932},{"time":1773797700,"open":626,"high":626,"low":626,"close":626,"volume":7310},{"time":1773797760,"open":626,"high":633,"low":626,"close":633,"volume":9581},{"time":1773797820,"open":633,"high":633,"low":631,"close":631,"volume":7337},{"time":1773797880,"open":631,"high":632,"low":627,"close":628,"volume":6458},{"time":1773797940,"open":628,"high":629,"low":626,"close":626,"volume":9877},{"time":1773798000,"open":626,"high":629,"low":626,"close":628,"volume":9785},{"time":1773798060,"open":628,"high":630,"low":628,"close":629,"volume":7909},{"time":1773798120,"open":629,"high":629,"low":628,"close":628,"volume":3583},{"time":1773798180,"open":628,"high":632,"low":627,"close":632,"volume":8357},{"time":1773798240,"open":632,"high":633,"low":626,"close":626,"volume":5957},{"time":1773798300,"open":626,"high":629,"low":626,"close":629,"volume":5621},{"time":1773798360,"open":629,"high":635,"low":628,"close":634,"volume":8955},{"time":1773798420,"open":634,"high":634,"low":629,"close":630,"volume":10296},{"time":1773798480,"open":630,"high":632,"low":629,"close":631,"volume":5374},{"time":1773798540,"open":631,"high":632,"low":627,"close":628,"volume":9712},{"time":1773798600,"open":628,"high":632,"low":627,"close":631,"volume":9172},{"time":1773798660,"open":631,"high":631,"low":626,"close":627,"volume":4702},{"time":1773798720,"open":627,"high":633,"low":626,"close":632,"volume":9078},{"time":1773798780,"open":632,"high":638,"low":632,"close":637,"volume":4226},{"time":1773798840,"open":637,"high":638,"low":630,"close":630,"volume":10240},{"time":1773798900,"open":630,"high":631,"low":629,"close":631,"volume":9748},{"time":1773798960,"open":631,"high":632,"low":626,"close":627,"volume":8732},{"time":1773799020,"open":627,"high":630,"low":627,"close":629,"volume":3881},{"time":1773799080,"open":629,"high":630,"low":627,"close":627,"volume":11331},{"time":1773799140,"open":627,"high":629,"low":626,"close":628,"volume":7666},{"time":1773799200,"open":628,"high":630,"low":627,"close":630,"volume":6845},{"time":1773799260,"open":630,"high":630,"low":629,"close":630,"volume":7376},{"time":1773799320,"open":630,"high":631,"low":628,"close":629,"volume":10766},{"time":1773799380,"open":629,"high":631,"low":628,"close":630,"volume":7270},{"time":1773799440,"open":630,"high":630,"low":630,"close":630,"volume":4396},{"time":1773799500,"open":630,"high":633,"low":629,"close":632,"volume":5329},{"time":1773799560,"open":632,"high":634,"low":631,"close":634,"volume":7395},{"time":1773799620,"open":634,"high":634,"low":630,"close":630,"volume":4535},{"time":1773799680,"open":630,"high":632,"low":630,"close":632,"volume":11469},{"time":1773799740,"open":632,"high":632,"low":631,"close":631,"volume":6803},{"time":1773799800,"open":631,"high":632,"low":628,"close":628,"volume":9208},{"time":1773799860,"open":628,"high":631,"low":627,"close":631,"volume":11573},{"time":1773799920,"open":631,"high":631,"low":626,"close":627,"volume":7770},{"time":1773799980,"open":627,"high":630,"low":626,"close":629,"volume":11342},{"time":1773800040,"open":629,"high":636,"low":628,"close":635,"volume":11334},{"time":1773800100,"open":635,"high":635,"low":626,"close":626,"volume":11917},{"time":1773800160,"open":626,"high":627,"low":626,"close":626,"volume":5899},{"time":1773800220,"open":626,"high":628,"low":626,"close":628,"volume":7166},{"time":1773800280,"open":628,"high":629,"low":626,"close":626,"volume":9964},{"time":1773800340,"open":626,"high":634,"low":626,"close":633,"volume":9561},{"time":1773800400,"open":633,"high":633,"low":626,"close":626,"volume":6582},{"time":1773800460,"open":626,"high":627,"low":626,"close":627,"volume":7851},{"time":1773800520,"open":627,"high":636,"low":626,"close":635,"volume":4406},{"time":1773800580,"open":635,"high":636,"low":629,"close":630,"volume":10678},{"time":1773800640,"open":630,"high":631,"low":626,"close":626,"volume":4874},{"time":1773800700,"open":626,"high":626,"low":626,"close":626,"volume":11016},{"time":1773800760,"open":626,"high":631,"low":626,"close":630,"volume":11991},{"time":1773800820,"open":630,"high":631,"low":630,"close":630,"volume":12719},{"time":1773800880,"open":630,"high":631,"low":628,"close":628,"volume":8782},{"time":1773800940,"open":628,"high":639,"low":627,"close":639,"volume":6335},{"time":1773801000,"open":639,"high":639,"low":629,"close":630,"volume":10746},{"time":1773801060,"open":630,"high":631,"low":629,"close":631,"volume":7672},{"time":1773801120,"open":631,"high":631,"low":628,"close":629,"volume":7689},{"time":1773801180,"open":629,"high":630,"low":626,"close":627,"volume":6952},{"time":1773801240,"open":627,"high":637,"low":626,"close":637,"volume":10144},{"time":1773801300,"open":637,"high":637,"low":626,"close":626,"volume":10964},{"time":1773801360,"open":626,"high":627,"low":626,"close":626,"volume":5575},{"time":1773801420,"open":626,"high":626,"low":626,"close":626,"volume":5314},{"time":1773801480,"open":626,"high":633,"low":626,"close":632,"volume":7495},{"time":1773801540,"open":632,"high":635,"low":631,"close":635,"volume":6490},{"time":1773801600,"open":635,"high":635,"low":626,"close":626,"volume":4969},{"time":1773801660,"open":626,"high":632,"low":626,"close":632,"volume":8729},{"time":1773801720,"open":632,"high":632,"low":628,"close":628,"volume":10826},{"time":1773801780,"open":628,"high":637,"low":627,"close":637,"volume":10724},{"time":1773801840,"open":637,"high":637,"low":630,"close":630,"volume":9301},{"time":1773801900,"open":630,"high":630,"low":629,"close":630,"volume":11921},{"time":1773801960,"open":630,"high":636,"low":629,"close":635,"volume":5707},{"time":1773802020,"open":635,"high":636,"low":626,"close":626,"volume":9020},{"time":1773802080,"open":626,"high":628,"low":626,"close":627,"volume":13205},{"time":1773802140,"open":627,"high":638,"low":626,"close":638,"volume":12636},{"time":1773802200,"open":638,"high":639,"low":636,"close":636,"volume":12493},{"time":1773802260,"open":636,"high":636,"low":629,"close":630,"volume":8155},{"time":1773802320,"open":630,"high":637,"low":629,"close":636,"volume":10608},{"time":1773802380,"open":636,"high":636,"low":633,"close":634,"volume":8906},{"time":1773802440,"open":634,"high":634,"low":629,"close":630,"volume":11305},{"time":1773802500,"open":630,"high":634,"low":629,"close":633,"volume":5129},{"time":1773802560,"open":633,"high":639,"low":633,"close":639,"volume":8805},{"time":1773802620,"open":639,"high":640,"low":627,"close":628,"volume":7282},{"time":1773802680,"open":628,"high":640,"low":627,"close":639,"volume":8034},{"time":1773802740,"open":639,"high":640,"low":628,"close":629,"volume":4833},{"time":1773802800,"open":629,"high":643,"low":628,"close":642,"volume":11901},{"time":1773802860,"open":642,"high":643,"low":632,"close":633,"volume":4806},{"time":1773802920,"open":633,"high":638,"low":631,"close":637,"volume":11690},{"time":1773802980,"open":637,"high":638,"low":628,"close":628,"volume":12440},{"time":1773803040,"open":628,"high":630,"low":627,"close":629,"volume":6155},{"time":1773803100,"open":629,"high":635,"low":628,"close":634,"volume":11462},{"time":1773803160,"open":634,"high":635,"low":626,"close":626,"volume":10567},{"time":1773803220,"open":626,"high":627,"low":626,"close":626,"volume":7826},{"time":1773803280,"open":626,"high":626,"low":626,"close":626,"volume":6402},{"time":1773803340,"open":626,"high":637,"low":626,"close":637,"volume":5547},{"time":1773803400,"open":637,"high":637,"low":630,"close":630,"volume":11216},{"time":1773803460,"open":630,"high":635,"low":630,"close":634,"volume":5060},{"time":1773803520,"open":634,"high":634,"low":630,"close":631,"volume":13082},{"time":1773803580,"open":631,"high":632,"low":630,"close":631,"volume":10139},{"time":1773803640,"open":631,"high":635,"low":631,"close":635,"volume":10998},{"time":1773803700,"open":635,"high":636,"low":627,"close":629,"volume":5301},{"time":1773803760,"open":629,"high":639,"low":628,"close":638,"volume":5835},{"time":1773803820,"open":638,"high":639,"low":632,"close":632,"volume":12283},{"time":1773803880,"open":632,"high":633,"low":626,"close":626,"volume":5807},{"time":1773803940,"open":626,"high":632,"low":626,"close":632,"volume":11611},{"time":1773804000,"open":632,"high":638,"low":631,"close":638,"volume":7326},{"time":1773804060,"open":638,"high":638,"low":628,"close":629,"volume":8574},{"time":1773804120,"open":629,"high":632,"low":628,"close":631,"volume":6165},{"time":1773804180,"open":631,"high":631,"low":627,"close":628,"volume":13132},{"time":1773804240,"open":628,"high":629,"low":627,"close":627,"volume":9040},{"time":1773804300,"open":627,"high":634,"low":627,"close":633,"volume":6948},{"time":1773804360,"open":633,"high":633,"low":631,"close":632,"volume":12038},{"time":1773804420,"open":632,"high":633,"low":629,"close":630,"volume":10501},{"time":1773804480,"open":630,"high":638,"low":629,"close":637,"volume":7636},{"time":1773804540,"open":637,"high":638,"low":630,"close":630,"volume":6035},{"time":1773804600,"open":630,"high":632,"low":629,"close":631,"volume":10091},{"time":1773804660,"open":631,"high":637,"low":630,"close":636,"volume":6065},{"time":1773804720,"open":636,"high":637,"low":635,"close":635,"volume":6154},{"time":1773804780,"open":635,"high":637,"low":635,"close":637,"volume":4723},{"time":1773804840,"open":637,"high":639,"low":635,"close":638,"volume":6246},{"time":1773804900,"open":638,"high":639,"low":633,"close":633,"volume":9920},{"time":1773804960,"open":633,"high":634,"low":626,"close":626,"volume":11629},{"time":1773805020,"open":626,"high":635,"low":626,"close":634,"volume":9016},{"time":1773805080,"open":634,"high":634,"low":633,"close":634,"volume":11547},{"time":1773805140,"open":634,"high":639,"low":633,"close":639,"volume":13461},{"time":1773805200,"open":639,"high":639,"low":626,"close":626,"volume":8969},{"time":1773805260,"open":626,"high":634,"low":626,"close":633,"volume":6334},{"time":1773805320,"open":633,"high":634,"low":628,"close":629,"volume":10926},{"time":1773805380,"open":629,"high":637,"low":628,"close":636,"volume":10112},{"time":1773805440,"open":636,"high":637,"low":633,"close":633,"volume":12016},{"time":1773805500,"open":633,"high":636,"low":633,"close":636,"volume":10031},{"time":1773805560,"open":636,"high":637,"low":635,"close":636,"volume":13050},{"time":1773805620,"open":636,"high":637,"low":635,"close":636,"volume":10387},{"time":1773805680,"open":636,"high":636,"low":628,"close":628,"volume":12288},{"time":1773805740,"open":628,"high":632,"low":627,"close":631,"volume":7942},{"time":1773805800,"open":631,"high":637,"low":630,"close":636,"volume":11349},{"time":1773805860,"open":636,"high":637,"low":632,"close":632,"volume":9246},{"time":1773805920,"open":632,"high":632,"low":630,"close":631,"volume":11377},{"time":1773805980,"open":631,"high":636,"low":630,"close":636,"volume":8087},{"time":1773806040,"open":636,"high":636,"low":631,"close":632,"volume":5244},{"time":1773806100,"open":632,"high":642,"low":631,"close":641,"volume":6944},{"time":1773806160,"open":641,"high":641,"low":630,"close":631,"volume":11071},{"time":1773806220,"open":631,"high":631,"low":628,"close":629,"volume":6957},{"time":1773806280,"open":629,"high":635,"low":629,"close":634,"volume":10702},{"time":1773806340,"open":634,"high":636,"low":634,"close":636,"volume":11767},{"time":1773806400,"open":636,"high":636,"low":630,"close":631,"volume":12378},{"time":1773806460,"open":631,"high":631,"low":627,"close":627,"volume":7893},{"time":1773806520,"open":627,"high":641,"low":626,"close":640,"volume":5021},{"time":1773806580,"open":640,"high":641,"low":633,"close":633,"volume":7416},{"time":1773806640,"open":633,"high":635,"low":632,"close":635,"volume":11778},{"time":1773806700,"open":635,"high":641,"low":634,"close":640,"volume":9953},{"time":1773806760,"open":640,"high":640,"low":634,"close":635,"volume":12253},{"time":1773806820,"open":635,"high":635,"low":634,"close":634,"volume":6412},{"time":1773806880,"open":634,"high":635,"low":634,"close":634,"volume":10045},{"time":1773806940,"open":634,"high":634,"low":632,"close":632,"volume":11266},{"time":1773807000,"open":632,"high":636,"low":631,"close":635,"volume":11740},{"time":1773807060,"open":635,"high":635,"low":627,"close":628,"volume":11163},{"time":1773807120,"open":628,"high":629,"low":627,"close":629,"volume":6492},{"time":1773807180,"open":629,"high":638,"low":627,"close":637,"volume":8702},{"time":1773807240,"open":637,"high":637,"low":631,"close":631,"volume":6514},{"time":1773807300,"open":631,"high":635,"low":631,"close":634,"volume":4379},{"time":1773807360,"open":634,"high":639,"low":634,"close":638,"volume":6994},{"time":1773807420,"open":638,"high":639,"low":627,"close":628,"volume":4863},{"time":1773807480,"open":628,"high":636,"low":626,"close":635,"volume":9325},{"time":1773807540,"open":635,"high":641,"low":634,"close":640,"volume":5333},{"time":1773807600,"open":640,"high":641,"low":632,"close":632,"volume":6279},{"time":1773807660,"open":632,"high":639,"low":632,"close":638,"volume":8782},{"time":1773807720,"open":638,"high":638,"low":633,"close":633,"volume":9561},{"time":1773807780,"open":633,"high":634,"low":630,"close":631,"volume":9547},{"time":1773807840,"open":631,"high":644,"low":630,"close":644,"volume":8063},{"time":1773807900,"open":644,"high":644,"low":636,"close":637,"volume":6872},{"time":1773807960,"open":637,"high":638,"low":635,"close":636,"volume":8703},{"time":1773808020,"open":636,"high":636,"low":633,"close":634,"volume":4194},{"time":1773808080,"open":634,"high":634,"low":628,"close":629,"volume":6007},{"time":1773808140,"open":629,"high":639,"low":628,"close":638,"volume":9042},{"time":1773808200,"open":638,"high":640,"low":637,"close":640,"volume":8026},{"time":1773808260,"open":640,"high":640,"low":628,"close":629,"volume":9917},{"time":1773808320,"open":629,"high":637,"low":628,"close":636,"volume":8021},{"time":1773808380,"open":636,"high":638,"low":632,"close":632,"volume":3931},{"time":1773808440,"open":632,"high":638,"low":632,"close":637,"volume":5065},{"time":1773808500,"open":637,"high":638,"low":632,"close":632,"volume":7231},{"time":1773808560,"open":632,"high":633,"low":632,"close":632,"volume":6654},{"time":1773808620,"open":632,"high":634,"low":632,"close":633,"volume":4952},{"time":1773808680,"open":633,"high":633,"low":632,"close":633,"volume":7727},{"time":1773808740,"open":633,"high":638,"low":632,"close":638,"volume":7569},{"time":1773808800,"open":638,"high":639,"low":635,"close":636,"volume":4223},{"time":1773808860,"open":636,"high":636,"low":634,"close":635,"volume":4170},{"time":1773808920,"open":635,"high":638,"low":634,"close":638,"volume":6355},{"time":1773808980,"open":638,"high":639,"low":635,"close":636,"volume":7067},{"time":1773809040,"open":636,"high":636,"low":632,"close":633,"volume":10377},{"time":1773809100,"open":633,"high":633,"low":628,"close":629,"volume":5054},{"time":1773809160,"open":629,"high":637,"low":628,"close":636,"volume":6051},{"time":1773809220,"open":636,"high":636,"low":627,"close":628,"volume":5967},{"time":1773809280,"open":628,"high":632,"low":627,"close":631,"volume":9420},{"time":1773809340,"open":631,"high":633,"low":630,"close":633,"volume":9692},{"time":1773809400,"open":633,"high":633,"low":631,"close":632,"volume":4726},{"time":1773809460,"open":632,"high":632,"low":631,"close":632,"volume":4900},{"time":1773809520,"open":632,"high":638,"low":632,"close":637,"volume":6177},{"time":1773809580,"open":637,"high":638,"low":634,"close":635,"volume":7863},{"time":1773809640,"open":635,"high":635,"low":629,"close":629,"volume":10082},{"time":1773809700,"open":629,"high":634,"low":628,"close":633,"volume":8463},{"time":1773809760,"open":633,"high":634,"low":633,"close":634,"volume":8781},{"time":1773809820,"open":634,"high":636,"low":633,"close":634,"volume":7953},{"time":1773809880,"open":634,"high":638,"low":634,"close":638,"volume":4987},{"time":1773809940,"open":638,"high":639,"low":634,"close":634,"volume":3416},{"time":1773810000,"open":634,"high":636,"low":634,"close":635,"volume":6878},{"time":1773810060,"open":635,"high":635,"low":629,"close":629,"volume":9301},{"time":1773810120,"open":629,"high":632,"low":629,"close":631,"volume":3832},{"time":1773810180,"open":631,"high":635,"low":630,"close":634,"volume":8750},{"time":1773810240,"open":634,"high":636,"low":634,"close":635,"volume":5595},{"time":1773810300,"open":635,"high":641,"low":635,"close":640,"volume":8290},{"time":1773810360,"open":640,"high":640,"low":635,"close":636,"volume":5257},{"time":1773810420,"open":636,"high":637,"low":634,"close":635,"volume":3993},{"time":1773810480,"open":635,"high":636,"low":634,"close":634,"volume":6347},{"time":1773810540,"open":634,"high":641,"low":634,"close":641,"volume":3689},{"time":1773810600,"open":641,"high":641,"low":638,"close":638,"volume":7933},{"time":1773810660,"open":638,"high":640,"low":638,"close":639,"volume":6740},{"time":1773810720,"open":639,"high":640,"low":631,"close":632,"volume":4630},{"time":1773810780,"open":632,"high":636,"low":631,"close":636,"volume":7642},{"time":1773810840,"open":636,"high":637,"low":635,"close":636,"volume":5264},{"time":1773810900,"open":636,"high":637,"low":632,"close":632,"volume":5069},{"time":1773810960,"open":632,"high":634,"low":631,"close":631,"volume":6616},{"time":1773811020,"open":631,"high":639,"low":631,"close":639,"volume":4342},{"time":1773811080,"open":639,"high":639,"low":635,"close":636,"volume":4382},{"time":1773811140,"open":636,"high":636,"low":634,"close":635,"volume":6814},{"time":1773811200,"open":635,"high":635,"low":634,"close":634,"volume":5706},{"time":1773811260,"open":634,"high":634,"low":634,"close":634,"volume":3287},{"time":1773811320,"open":634,"high":636,"low":634,"close":636,"volume":4146},{"time":1773811380,"open":636,"high":639,"low":635,"close":638,"volume":7101},{"time":1773811440,"open":638,"high":639,"low":632,"close":633,"volume":3515},{"time":1773811500,"open":633,"high":637,"low":632,"close":636,"volume":3668},{"time":1773811560,"open":636,"high":637,"low":632,"close":632,"volume":5642},{"time":1773811620,"open":632,"high":634,"low":632,"close":633,"volume":4735},{"time":1773811680,"open":633,"high":639,"low":633,"close":638,"volume":3895},{"time":1773811740,"open":638,"high":639,"low":633,"close":634,"volume":6741},{"time":1773811800,"open":634,"high":638,"low":634,"close":637,"volume":3152},{"time":1773811860,"open":637,"high":638,"low":634,"close":635,"volume":7903},{"time":1773811920,"open":635,"high":637,"low":635,"close":637,"volume":5987},{"time":1773811980,"open":637,"high":638,"low":633,"close":634,"volume":3845},{"time":1773812040,"open":634,"high":636,"low":634,"close":636,"volume":4529},{"time":1773812100,"open":636,"high":637,"low":632,"close":633,"volume":4373},{"time":1773812160,"open":633,"high":634,"low":630,"close":631,"volume":7863},{"time":1773812220,"open":631,"high":632,"low":630,"close":631,"volume":3917},{"time":1773812280,"open":631,"high":635,"low":631,"close":634,"volume":2871},{"time":1773812340,"open":634,"high":637,"low":633,"close":636,"volume":4028},{"time":1773812400,"open":636,"high":637,"low":633,"close":633,"volume":5419},{"time":1773812460,"open":633,"high":636,"low":633,"close":635,"volume":3315},{"time":1773812520,"open":635,"high":641,"low":635,"close":640,"volume":4726},{"time":1773812580,"open":640,"high":641,"low":640,"close":640,"volume":4783},{"time":1773812640,"open":640,"high":640,"low":636,"close":637,"volume":5490},{"time":1773812700,"open":637,"high":638,"low":637,"close":638,"volume":4331},{"time":1773812760,"open":638,"high":639,"low":633,"close":634,"volume":7139},{"time":1773812820,"open":634,"high":637,"low":634,"close":636,"volume":4907},{"time":1773812880,"open":636,"high":640,"low":636,"close":639,"volume":5099},{"time":1773812940,"open":639,"high":640,"low":639,"close":639,"volume":7472},{"time":1773813000,"open":639,"high":640,"low":634,"close":634,"volume":4417},{"time":1773813060,"open":634,"high":638,"low":633,"close":638,"volume":6341},{"time":1773813120,"open":638,"high":638,"low":633,"close":634,"volume":3315},{"time":1773813180,"open":634,"high":641,"low":633,"close":640,"volume":6780},{"time":1773813240,"open":640,"high":640,"low":637,"close":638,"volume":4139},{"time":1773813300,"open":638,"high":639,"low":637,"close":637,"volume":7078},{"time":1773813360,"open":637,"high":638,"low":636,"close":638,"volume":3011},{"time":1773813420,"open":638,"high":639,"low":631,"close":631,"volume":5730},{"time":1773813480,"open":631,"high":636,"low":631,"close":635,"volume":5671},{"time":1773813540,"open":635,"high":637,"low":634,"close":637,"volume":6592},{"time":1773813600,"open":637,"high":638,"low":636,"close":638,"volume":6720},{"time":1773813660,"open":638,"high":640,"low":636,"close":639,"volume":6591},{"time":1773813720,"open":639,"high":639,"low":637,"close":637,"volume":2891},{"time":1773813780,"open":637,"high":639,"low":637,"close":638,"volume":5026},{"time":1773813840,"open":638,"high":639,"low":635,"close":636,"volume":3580},{"time":1773813900,"open":636,"high":637,"low":635,"close":636,"volume":4538},{"time":1773813960,"open":636,"high":638,"low":635,"close":635,"volume":6841},{"time":1773814020,"open":635,"high":638,"low":634,"close":637,"volume":4630},{"time":1773814080,"open":637,"high":638,"low":633,"close":634,"volume":3471},{"time":1773814140,"open":634,"high":635,"low":632,"close":633,"volume":6457},{"time":1773814200,"open":633,"high":638,"low":633,"close":638,"volume":6109},{"time":1773814260,"open":638,"high":638,"low":635,"close":636,"volume":6979},{"time":1773814320,"open":636,"high":637,"low":635,"close":635,"volume":3934},{"time":1773814380,"open":635,"high":637,"low":634,"close":637,"volume":3328},{"time":1773814440,"open":637,"high":639,"low":636,"close":638,"volume":4583},{"time":1773814500,"open":638,"high":639,"low":633,"close":634,"volume":2612},{"time":1773814560,"open":634,"high":639,"low":634,"close":638,"volume":2712},{"time":1773814620,"open":638,"high":639,"low":636,"close":637,"volume":3017},{"time":1773814680,"open":637,"high":639,"low":636,"close":638,"volume":6200},{"time":1773814740,"open":638,"high":639,"low":636,"close":636,"volume":5028},{"time":1773814800,"open":636,"high":638,"low":636,"close":637,"volume":3073},{"time":1773814860,"open":637,"high":637,"low":635,"close":635,"volume":3559},{"time":1773814920,"open":635,"high":637,"low":635,"close":636,"volume":6667},{"time":1773814980,"open":636,"high":637,"low":636,"close":636,"volume":6447},{"time":1773815040,"open":636,"high":637,"low":635,"close":636,"volume":4365},{"time":1773815100,"open":636,"high":638,"low":635,"close":637,"volume":2809},{"time":1773815160,"open":637,"high":638,"low":635,"close":636,"volume":6703},{"time":1773815220,"open":636,"high":637,"low":635,"close":636,"volume":6403},{"time":1773815280,"open":636,"high":638,"low":636,"close":637,"volume":6484},{"time":1773815340,"open":637,"high":638,"low":637,"close":637,"volume":6579},{"time":1773878400,"open":644,"high":644,"low":643,"close":644,"volume":1130},{"time":1773878460,"open":644,"high":644,"low":643,"close":644,"volume":745},{"time":1773878520,"open":644,"high":644,"low":643,"close":644,"volume":599},{"time":1773878580,"open":644,"high":644,"low":644,"close":644,"volume":979},{"time":1773878640,"open":644,"high":644,"low":643,"close":644,"volume":939},{"time":1773878700,"open":644,"high":644,"low":643,"close":644,"volume":920},{"time":1773878760,"open":644,"high":644,"low":643,"close":644,"volume":855},{"time":1773878820,"open":644,"high":644,"low":643,"close":644,"volume":1008},{"time":1773878880,"open":644,"high":644,"low":642,"close":644,"volume":1125},{"time":1773878940,"open":644,"high":644,"low":642,"close":644,"volume":1133},{"time":1773879000,"open":644,"high":644,"low":644,"close":644,"volume":1052},{"time":1773879060,"open":644,"high":644,"low":644,"close":644,"volume":1113},{"time":1773879120,"open":644,"high":644,"low":643,"close":644,"volume":435},{"time":1773879180,"open":644,"high":644,"low":644,"close":644,"volume":1056},{"time":1773879240,"open":644,"high":644,"low":643,"close":644,"volume":592},{"time":1773879300,"open":644,"high":644,"low":644,"close":644,"volume":836},{"time":1773879360,"open":644,"high":644,"low":643,"close":644,"volume":987},{"time":1773879420,"open":644,"high":644,"low":643,"close":644,"volume":1053},{"time":1773879480,"open":644,"high":644,"low":643,"close":644,"volume":903},{"time":1773879540,"open":644,"high":644,"low":643,"close":644,"volume":1179},{"time":1773879600,"open":644,"high":644,"low":643,"close":643,"volume":491},{"time":1773879660,"open":643,"high":644,"low":643,"close":644,"volume":1014},{"time":1773879720,"open":644,"high":644,"low":643,"close":644,"volume":662},{"time":1773879780,"open":644,"high":644,"low":642,"close":643,"volume":430},{"time":1773879840,"open":643,"high":644,"low":642,"close":643,"volume":867},{"time":1773879900,"open":643,"high":644,"low":643,"close":644,"volume":1209},{"time":1773879960,"open":644,"high":644,"low":642,"close":643,"volume":1220},{"time":1773880020,"open":643,"high":644,"low":642,"close":644,"volume":1063},{"time":1773880080,"open":644,"high":644,"low":642,"close":643,"volume":1222},{"time":1773880140,"open":643,"high":644,"low":642,"close":644,"volume":770},{"time":1773880200,"open":644,"high":644,"low":643,"close":644,"volume":1013},{"time":1773880260,"open":644,"high":644,"low":642,"close":643,"volume":630},{"time":1773880320,"open":643,"high":644,"low":641,"close":642,"volume":814},{"time":1773880380,"open":642,"high":644,"low":642,"close":644,"volume":746},{"time":1773880440,"open":644,"high":644,"low":642,"close":643,"volume":657},{"time":1773880500,"open":643,"high":644,"low":642,"close":644,"volume":599},{"time":1773880560,"open":644,"high":644,"low":642,"close":643,"volume":704},{"time":1773880620,"open":643,"high":644,"low":641,"close":643,"volume":678},{"time":1773880680,"open":643,"high":644,"low":642,"close":643,"volume":1149},{"time":1773880740,"open":643,"high":644,"low":642,"close":643,"volume":1222},{"time":1773880800,"open":643,"high":643,"low":642,"close":642,"volume":1118},{"time":1773880860,"open":642,"high":643,"low":641,"close":643,"volume":1228},{"time":1773880920,"open":643,"high":644,"low":641,"close":642,"volume":736},{"time":1773880980,"open":642,"high":643,"low":642,"close":642,"volume":800},{"time":1773881040,"open":642,"high":643,"low":641,"close":643,"volume":986},{"time":1773881100,"open":643,"high":644,"low":642,"close":643,"volume":1080},{"time":1773881160,"open":643,"high":644,"low":642,"close":643,"volume":621},{"time":1773881220,"open":643,"high":644,"low":641,"close":642,"volume":588},{"time":1773881280,"open":642,"high":643,"low":642,"close":643,"volume":576},{"time":1773881340,"open":643,"high":643,"low":642,"close":642,"volume":967},{"time":1773881400,"open":642,"high":643,"low":641,"close":642,"volume":706},{"time":1773881460,"open":642,"high":642,"low":641,"close":642,"volume":788},{"time":1773881520,"open":642,"high":643,"low":641,"close":643,"volume":857},{"time":1773881580,"open":643,"high":644,"low":642,"close":643,"volume":534},{"time":1773881640,"open":643,"high":644,"low":642,"close":642,"volume":1149},{"time":1773881700,"open":642,"high":644,"low":641,"close":642,"volume":893},{"time":1773881760,"open":642,"high":643,"low":642,"close":643,"volume":520},{"time":1773881820,"open":643,"high":644,"low":642,"close":642,"volume":710},{"time":1773881880,"open":642,"high":643,"low":641,"close":642,"volume":1192},{"time":1773881940,"open":642,"high":643,"low":641,"close":642,"volume":1356},{"time":1773882000,"open":642,"high":644,"low":641,"close":643,"volume":1062},{"time":1773882060,"open":643,"high":643,"low":641,"close":642,"volume":1393},{"time":1773882120,"open":642,"high":643,"low":641,"close":642,"volume":739},{"time":1773882180,"open":642,"high":643,"low":641,"close":643,"volume":560},{"time":1773882240,"open":643,"high":643,"low":640,"close":641,"volume":1424},{"time":1773882300,"open":641,"high":642,"low":641,"close":642,"volume":1393},{"time":1773882360,"open":642,"high":644,"low":641,"close":643,"volume":508},{"time":1773882420,"open":643,"high":644,"low":641,"close":642,"volume":499},{"time":1773882480,"open":642,"high":643,"low":639,"close":640,"volume":1020},{"time":1773882540,"open":640,"high":642,"low":640,"close":642,"volume":868},{"time":1773882600,"open":642,"high":643,"low":641,"close":643,"volume":1014},{"time":1773882660,"open":643,"high":643,"low":641,"close":642,"volume":835},{"time":1773882720,"open":642,"high":643,"low":641,"close":642,"volume":567},{"time":1773882780,"open":642,"high":643,"low":642,"close":642,"volume":867},{"time":1773882840,"open":642,"high":643,"low":639,"close":640,"volume":1155},{"time":1773882900,"open":640,"high":644,"low":639,"close":643,"volume":1145},{"time":1773882960,"open":643,"high":644,"low":642,"close":642,"volume":889},{"time":1773883020,"open":642,"high":643,"low":642,"close":642,"volume":702},{"time":1773883080,"open":642,"high":643,"low":641,"close":641,"volume":1581},{"time":1773883140,"open":641,"high":644,"low":640,"close":643,"volume":1357},{"time":1773883200,"open":643,"high":644,"low":642,"close":642,"volume":820},{"time":1773883260,"open":642,"high":643,"low":639,"close":640,"volume":1518},{"time":1773883320,"open":640,"high":643,"low":640,"close":641,"volume":1527},{"time":1773883380,"open":641,"high":642,"low":640,"close":642,"volume":1333},{"time":1773883440,"open":642,"high":642,"low":641,"close":642,"volume":557},{"time":1773883500,"open":642,"high":642,"low":642,"close":642,"volume":1334},{"time":1773883560,"open":642,"high":643,"low":641,"close":641,"volume":728},{"time":1773883620,"open":641,"high":642,"low":640,"close":642,"volume":1522},{"time":1773883680,"open":642,"high":642,"low":642,"close":642,"volume":641},{"time":1773883740,"open":642,"high":642,"low":641,"close":642,"volume":1668},{"time":1773883800,"open":642,"high":642,"low":641,"close":641,"volume":1554},{"time":1773883860,"open":641,"high":642,"low":641,"close":641,"volume":1249},{"time":1773883920,"open":641,"high":644,"low":640,"close":643,"volume":1588},{"time":1773883980,"open":643,"high":644,"low":643,"close":644,"volume":659},{"time":1773884040,"open":644,"high":644,"low":641,"close":642,"volume":1201},{"time":1773884100,"open":642,"high":644,"low":641,"close":643,"volume":1077},{"time":1773884160,"open":643,"high":643,"low":642,"close":642,"volume":1028},{"time":1773884220,"open":642,"high":643,"low":640,"close":641,"volume":1622},{"time":1773884280,"open":641,"high":644,"low":641,"close":644,"volume":1518},{"time":1773884340,"open":644,"high":644,"low":640,"close":641,"volume":1669},{"time":1773884400,"open":641,"high":643,"low":641,"close":642,"volume":984},{"time":1773884460,"open":642,"high":642,"low":639,"close":640,"volume":872},{"time":1773884520,"open":640,"high":642,"low":640,"close":641,"volume":1704},{"time":1773884580,"open":641,"high":643,"low":640,"close":642,"volume":1529},{"time":1773884640,"open":642,"high":643,"low":641,"close":641,"volume":1619},{"time":1773884700,"open":641,"high":643,"low":641,"close":642,"volume":1415},{"time":1773884760,"open":642,"high":643,"low":639,"close":640,"volume":1754},{"time":1773884820,"open":640,"high":640,"low":639,"close":640,"volume":816},{"time":1773884880,"open":640,"high":641,"low":639,"close":641,"volume":1477},{"time":1773884940,"open":641,"high":643,"low":641,"close":642,"volume":1696},{"time":1773885000,"open":642,"high":643,"low":639,"close":639,"volume":1514},{"time":1773885060,"open":639,"high":640,"low":639,"close":640,"volume":633},{"time":1773885120,"open":640,"high":641,"low":639,"close":641,"volume":1240},{"time":1773885180,"open":641,"high":644,"low":640,"close":643,"volume":676},{"time":1773885240,"open":643,"high":643,"low":639,"close":640,"volume":1261},{"time":1773885300,"open":640,"high":643,"low":639,"close":643,"volume":1232},{"time":1773885360,"open":643,"high":644,"low":640,"close":641,"volume":1516},{"time":1773885420,"open":641,"high":643,"low":640,"close":642,"volume":1387},{"time":1773885480,"open":642,"high":644,"low":640,"close":640,"volume":1321},{"time":1773885540,"open":640,"high":642,"low":640,"close":641,"volume":1685},{"time":1773885600,"open":641,"high":642,"low":640,"close":641,"volume":1011},{"time":1773885660,"open":641,"high":642,"low":639,"close":640,"volume":1354},{"time":1773885720,"open":640,"high":642,"low":639,"close":641,"volume":1357},{"time":1773885780,"open":641,"high":642,"low":639,"close":640,"volume":1291},{"time":1773885840,"open":640,"high":642,"low":640,"close":642,"volume":763},{"time":1773885900,"open":642,"high":643,"low":640,"close":640,"volume":1408},{"time":1773885960,"open":640,"high":641,"low":639,"close":640,"volume":1985},{"time":1773886020,"open":640,"high":641,"low":639,"close":640,"volume":1205},{"time":1773886080,"open":640,"high":641,"low":639,"close":641,"volume":1664},{"time":1773886140,"open":641,"high":641,"low":640,"close":641,"volume":991},{"time":1773886200,"open":641,"high":641,"low":639,"close":639,"volume":707},{"time":1773886260,"open":639,"high":640,"low":639,"close":639,"volume":1604},{"time":1773886320,"open":639,"high":640,"low":638,"close":640,"volume":1710},{"time":1773886380,"open":640,"high":641,"low":639,"close":639,"volume":1837},{"time":1773886440,"open":639,"high":641,"low":638,"close":641,"volume":1902},{"time":1773886500,"open":641,"high":641,"low":639,"close":640,"volume":1953},{"time":1773886560,"open":640,"high":640,"low":639,"close":640,"volume":1896},{"time":1773886620,"open":640,"high":641,"low":638,"close":639,"volume":717},{"time":1773886680,"open":639,"high":641,"low":638,"close":640,"volume":1288},{"time":1773886740,"open":640,"high":641,"low":639,"close":640,"volume":1697},{"time":1773886800,"open":640,"high":641,"low":638,"close":639,"volume":1937},{"time":1773886860,"open":639,"high":641,"low":638,"close":640,"volume":1798},{"time":1773886920,"open":640,"high":641,"low":638,"close":638,"volume":2010},{"time":1773886980,"open":638,"high":641,"low":638,"close":640,"volume":1216},{"time":1773887040,"open":640,"high":641,"low":639,"close":641,"volume":918},{"time":1773887100,"open":641,"high":641,"low":639,"close":640,"volume":1340},{"time":1773887160,"open":640,"high":642,"low":639,"close":641,"volume":1086},{"time":1773887220,"open":641,"high":641,"low":640,"close":640,"volume":1834},{"time":1773887280,"open":640,"high":641,"low":638,"close":638,"volume":2139},{"time":1773887340,"open":638,"high":640,"low":638,"close":640,"volume":1765},{"time":1773887400,"open":640,"high":641,"low":639,"close":640,"volume":1010},{"time":1773887460,"open":640,"high":641,"low":640,"close":640,"volume":985},{"time":1773887520,"open":640,"high":641,"low":637,"close":639,"volume":1901},{"time":1773887580,"open":639,"high":640,"low":638,"close":638,"volume":830},{"time":1773887640,"open":638,"high":640,"low":637,"close":640,"volume":955},{"time":1773887700,"open":640,"high":643,"low":639,"close":641,"volume":1705},{"time":1773887760,"open":641,"high":642,"low":640,"close":640,"volume":1889},{"time":1773887820,"open":640,"high":642,"low":639,"close":641,"volume":1016},{"time":1773887880,"open":641,"high":642,"low":638,"close":639,"volume":845},{"time":1773887940,"open":639,"high":640,"low":637,"close":638,"volume":1348},{"time":1773888000,"open":638,"high":640,"low":637,"close":639,"volume":1565},{"time":1773888060,"open":639,"high":641,"low":638,"close":641,"volume":2230},{"time":1773888120,"open":641,"high":641,"low":640,"close":640,"volume":1472},{"time":1773888180,"open":640,"high":641,"low":639,"close":641,"volume":1304},{"time":1773888240,"open":641,"high":641,"low":637,"close":638,"volume":1602},{"time":1773888300,"open":638,"high":639,"low":636,"close":637,"volume":1940},{"time":1773888360,"open":637,"high":639,"low":636,"close":638,"volume":1052},{"time":1773888420,"open":638,"high":642,"low":637,"close":641,"volume":1498},{"time":1773888480,"open":641,"high":642,"low":637,"close":638,"volume":910},{"time":1773888540,"open":638,"high":639,"low":637,"close":638,"volume":2076},{"time":1773888600,"open":638,"high":638,"low":636,"close":637,"volume":1589},{"time":1773888660,"open":637,"high":639,"low":636,"close":638,"volume":2213},{"time":1773888720,"open":638,"high":642,"low":637,"close":641,"volume":1817},{"time":1773888780,"open":641,"high":642,"low":638,"close":639,"volume":1847},{"time":1773888840,"open":639,"high":640,"low":637,"close":637,"volume":1496},{"time":1773888900,"open":637,"high":640,"low":637,"close":640,"volume":1415},{"time":1773888960,"open":640,"high":642,"low":640,"close":640,"volume":2132},{"time":1773889020,"open":640,"high":641,"low":639,"close":639,"volume":2009},{"time":1773889080,"open":639,"high":640,"low":638,"close":639,"volume":1063},{"time":1773889140,"open":639,"high":639,"low":638,"close":639,"volume":1005},{"time":1773889200,"open":639,"high":639,"low":638,"close":639,"volume":822},{"time":1773889260,"open":639,"high":639,"low":638,"close":639,"volume":830},{"time":1773889320,"open":639,"high":639,"low":638,"close":639,"volume":2025},{"time":1773889380,"open":639,"high":639,"low":637,"close":638,"volume":2063},{"time":1773889440,"open":638,"high":639,"low":635,"close":636,"volume":1097},{"time":1773889500,"open":636,"high":640,"low":635,"close":640,"volume":1787},{"time":1773889560,"open":640,"high":641,"low":639,"close":640,"volume":1910},{"time":1773889620,"open":640,"high":641,"low":638,"close":639,"volume":967},{"time":1773889680,"open":639,"high":640,"low":638,"close":639,"volume":2104},{"time":1773889740,"open":639,"high":639,"low":639,"close":639,"volume":2054},{"time":1773889800,"open":639,"high":640,"low":638,"close":638,"volume":1851},{"time":1773889860,"open":638,"high":639,"low":638,"close":639,"volume":1425},{"time":1773889920,"open":639,"high":639,"low":636,"close":636,"volume":1061},{"time":1773889980,"open":636,"high":640,"low":636,"close":639,"volume":1740},{"time":1773890040,"open":639,"high":640,"low":637,"close":637,"volume":2265},{"time":1773890100,"open":637,"high":639,"low":636,"close":639,"volume":1082},{"time":1773890160,"open":639,"high":640,"low":638,"close":638,"volume":1314},{"time":1773890220,"open":638,"high":639,"low":636,"close":637,"volume":1606},{"time":1773890280,"open":637,"high":639,"low":637,"close":639,"volume":1847},{"time":1773890340,"open":639,"high":640,"low":637,"close":638,"volume":1151},{"time":1773890400,"open":638,"high":638,"low":637,"close":637,"volume":2018},{"time":1773890460,"open":637,"high":638,"low":636,"close":637,"volume":2158},{"time":1773890520,"open":637,"high":639,"low":636,"close":639,"volume":1440},{"time":1773890580,"open":639,"high":640,"low":637,"close":638,"volume":2207},{"time":1773890640,"open":638,"high":639,"low":636,"close":636,"volume":1333},{"time":1773890700,"open":636,"high":637,"low":636,"close":636,"volume":1402},{"time":1773890760,"open":636,"high":639,"low":635,"close":638,"volume":1167},{"time":1773890820,"open":638,"high":639,"low":638,"close":639,"volume":1407},{"time":1773890880,"open":639,"high":641,"low":639,"close":640,"volume":1601},{"time":1773890940,"open":640,"high":641,"low":637,"close":639,"volume":1803},{"time":1773891000,"open":639,"high":639,"low":638,"close":639,"volume":1576},{"time":1773891060,"open":639,"high":640,"low":637,"close":638,"volume":1867},{"time":1773891120,"open":638,"high":639,"low":638,"close":639,"volume":1989},{"time":1773891180,"open":639,"high":641,"low":637,"close":640,"volume":2176},{"time":1773891240,"open":640,"high":641,"low":639,"close":639,"volume":1274},{"time":1773891300,"open":639,"high":640,"low":637,"close":638,"volume":1519},{"time":1773891360,"open":638,"high":639,"low":637,"close":638,"volume":1263},{"time":1773891420,"open":638,"high":639,"low":638,"close":638,"volume":1766},{"time":1773891480,"open":638,"high":638,"low":637,"close":638,"volume":912},{"time":1773891540,"open":638,"high":639,"low":637,"close":638,"volume":1118},{"time":1773891600,"open":638,"high":640,"low":638,"close":640,"volume":932},{"time":1773891660,"open":640,"high":640,"low":638,"close":639,"volume":838},{"time":1773891720,"open":639,"high":640,"low":637,"close":637,"volume":1417},{"time":1773891780,"open":637,"high":638,"low":636,"close":637,"volume":1653},{"time":1773891840,"open":637,"high":639,"low":636,"close":638,"volume":973},{"time":1773891900,"open":638,"high":639,"low":638,"close":638,"volume":1447},{"time":1773891960,"open":638,"high":639,"low":636,"close":637,"volume":2032},{"time":1773892020,"open":637,"high":637,"low":635,"close":635,"volume":1652},{"time":1773892080,"open":635,"high":641,"low":635,"close":641,"volume":1690},{"time":1773892140,"open":641,"high":642,"low":635,"close":635,"volume":1289},{"time":1773892200,"open":635,"high":637,"low":635,"close":636,"volume":1137},{"time":1773892260,"open":636,"high":638,"low":635,"close":637,"volume":1458},{"time":1773892320,"open":637,"high":638,"low":636,"close":638,"volume":2198},{"time":1773892380,"open":638,"high":638,"low":636,"close":637,"volume":1431},{"time":1773892440,"open":637,"high":638,"low":635,"close":636,"volume":798},{"time":1773892500,"open":636,"high":639,"low":636,"close":638,"volume":1812},{"time":1773892560,"open":638,"high":640,"low":637,"close":639,"volume":1349},{"time":1773892620,"open":639,"high":640,"low":636,"close":637,"volume":1376},{"time":1773892680,"open":637,"high":638,"low":635,"close":637,"volume":1965},{"time":1773892740,"open":637,"high":638,"low":635,"close":636,"volume":1876},{"time":1773892800,"open":636,"high":638,"low":635,"close":638,"volume":1900},{"time":1773892860,"open":638,"high":638,"low":636,"close":637,"volume":1008},{"time":1773892920,"open":637,"high":638,"low":636,"close":637,"volume":2003},{"time":1773892980,"open":637,"high":637,"low":635,"close":636,"volume":1477},{"time":1773893040,"open":636,"high":637,"low":633,"close":634,"volume":1034},{"time":1773893100,"open":634,"high":637,"low":633,"close":637,"volume":1076},{"time":1773893160,"open":637,"high":638,"low":635,"close":638,"volume":1034},{"time":1773893220,"open":638,"high":638,"low":636,"close":637,"volume":829},{"time":1773893280,"open":637,"high":638,"low":636,"close":638,"volume":2122},{"time":1773893340,"open":638,"high":639,"low":636,"close":637,"volume":1683},{"time":1773893400,"open":637,"high":638,"low":637,"close":637,"volume":941},{"time":1773893460,"open":637,"high":639,"low":637,"close":638,"volume":1508},{"time":1773893520,"open":638,"high":638,"low":637,"close":638,"volume":1930},{"time":1773893580,"open":638,"high":639,"low":637,"close":638,"volume":752},{"time":1773893640,"open":638,"high":638,"low":635,"close":635,"volume":1404},{"time":1773893700,"open":635,"high":637,"low":634,"close":636,"volume":1425},{"time":1773893760,"open":636,"high":637,"low":635,"close":635,"volume":853},{"time":1773893820,"open":635,"high":638,"low":635,"close":638,"volume":1470},{"time":1773893880,"open":638,"high":639,"low":636,"close":636,"volume":1163},{"time":1773893940,"open":636,"high":637,"low":635,"close":636,"volume":1449},{"time":1773894000,"open":636,"high":637,"low":636,"close":636,"volume":1802},{"time":1773894060,"open":636,"high":637,"low":635,"close":636,"volume":1244},{"time":1773894120,"open":636,"high":638,"low":635,"close":637,"volume":1052},{"time":1773894180,"open":637,"high":638,"low":635,"close":635,"volume":2007},{"time":1773894240,"open":635,"high":639,"low":635,"close":637,"volume":1276},{"time":1773894300,"open":637,"high":639,"low":637,"close":638,"volume":872},{"time":1773894360,"open":638,"high":639,"low":637,"close":637,"volume":1358},{"time":1773894420,"open":637,"high":637,"low":636,"close":637,"volume":1847},{"time":1773894480,"open":637,"high":637,"low":636,"close":636,"volume":1491},{"time":1773894540,"open":636,"high":637,"low":636,"close":636,"volume":868},{"time":1773894600,"open":636,"high":636,"low":636,"close":636,"volume":1876},{"time":1773894660,"open":636,"high":637,"low":636,"close":637,"volume":1920},{"time":1773894720,"open":637,"high":637,"low":636,"close":637,"volume":1047},{"time":1773894780,"open":637,"high":637,"low":634,"close":635,"volume":1900},{"time":1773894840,"open":635,"high":637,"low":635,"close":637,"volume":1507},{"time":1773894900,"open":637,"high":637,"low":634,"close":636,"volume":1021},{"time":1773894960,"open":636,"high":638,"low":635,"close":637,"volume":1863},{"time":1773895020,"open":637,"high":638,"low":635,"close":637,"volume":717},{"time":1773895080,"open":637,"high":638,"low":636,"close":636,"volume":872},{"time":1773895140,"open":636,"high":636,"low":635,"close":636,"volume":1426},{"time":1773895200,"open":636,"high":639,"low":635,"close":638,"volume":626},{"time":1773895260,"open":638,"high":639,"low":636,"close":637,"volume":1628},{"time":1773895320,"open":637,"high":637,"low":634,"close":635,"volume":1453},{"time":1773895380,"open":635,"high":636,"low":634,"close":634,"volume":810},{"time":1773895440,"open":634,"high":638,"low":634,"close":637,"volume":894},{"time":1773895500,"open":637,"high":637,"low":634,"close":635,"volume":1145},{"time":1773895560,"open":635,"high":636,"low":634,"close":635,"volume":954},{"time":1773895620,"open":635,"high":636,"low":633,"close":634,"volume":876},{"time":1773895680,"open":634,"high":636,"low":633,"close":636,"volume":1562},{"time":1773895740,"open":636,"high":636,"low":635,"close":635,"volume":1739},{"time":1773895800,"open":635,"high":636,"low":634,"close":634,"volume":997},{"time":1773895860,"open":634,"high":637,"low":634,"close":637,"volume":1748},{"time":1773895920,"open":637,"high":637,"low":635,"close":636,"volume":600},{"time":1773895980,"open":636,"high":638,"low":634,"close":635,"volume":807},{"time":1773896040,"open":635,"high":636,"low":635,"close":635,"volume":1557},{"time":1773896100,"open":635,"high":638,"low":635,"close":637,"volume":840},{"time":1773896160,"open":637,"high":637,"low":634,"close":635,"volume":953},{"time":1773896220,"open":635,"high":636,"low":634,"close":634,"volume":729},{"time":1773896280,"open":634,"high":636,"low":634,"close":635,"volume":1698},{"time":1773896340,"open":635,"high":638,"low":634,"close":638,"volume":1578},{"time":1773896400,"open":638,"high":639,"low":637,"close":637,"volume":1133},{"time":1773896460,"open":637,"high":638,"low":636,"close":637,"volume":714},{"time":1773896520,"open":637,"high":638,"low":633,"close":634,"volume":818},{"time":1773896580,"open":634,"high":637,"low":634,"close":636,"volume":1649},{"time":1773896640,"open":636,"high":636,"low":633,"close":634,"volume":856},{"time":1773896700,"open":634,"high":637,"low":633,"close":637,"volume":602},{"time":1773896760,"open":637,"high":638,"low":634,"close":634,"volume":1493},{"time":1773896820,"open":634,"high":638,"low":634,"close":638,"volume":671},{"time":1773896880,"open":638,"high":639,"low":634,"close":636,"volume":692},{"time":1773896940,"open":636,"high":636,"low":635,"close":635,"volume":985},{"time":1773897000,"open":635,"high":636,"low":635,"close":636,"volume":1133},{"time":1773897060,"open":636,"high":637,"low":634,"close":634,"volume":528},{"time":1773897120,"open":634,"high":636,"low":634,"close":636,"volume":973},{"time":1773897180,"open":636,"high":636,"low":635,"close":635,"volume":784},{"time":1773897240,"open":635,"high":637,"low":635,"close":636,"volume":1089},{"time":1773897300,"open":636,"high":637,"low":636,"close":636,"volume":791},{"time":1773897360,"open":636,"high":637,"low":633,"close":635,"volume":870},{"time":1773897420,"open":635,"high":636,"low":633,"close":634,"volume":547},{"time":1773897480,"open":634,"high":637,"low":633,"close":636,"volume":961},{"time":1773897540,"open":636,"high":636,"low":634,"close":635,"volume":1182},{"time":1773897600,"open":635,"high":635,"low":634,"close":635,"volume":788},{"time":1773897660,"open":635,"high":635,"low":634,"close":635,"volume":1396},{"time":1773897720,"open":635,"high":636,"low":634,"close":635,"volume":763},{"time":1773897780,"open":635,"high":635,"low":633,"close":634,"volume":1157},{"time":1773897840,"open":634,"high":635,"low":634,"close":634,"volume":1003},{"time":1773897900,"open":634,"high":635,"low":633,"close":635,"volume":864},{"time":1773897960,"open":635,"high":635,"low":635,"close":635,"volume":1221},{"time":1773898020,"open":635,"high":636,"low":634,"close":635,"volume":1253},{"time":1773898080,"open":635,"high":635,"low":634,"close":634,"volume":965},{"time":1773898140,"open":634,"high":635,"low":634,"close":635,"volume":886},{"time":1773898200,"open":635,"high":636,"low":634,"close":634,"volume":776},{"time":1773898260,"open":634,"high":636,"low":633,"close":634,"volume":1080},{"time":1773898320,"open":634,"high":634,"low":633,"close":633,"volume":573},{"time":1773898380,"open":633,"high":635,"low":632,"close":634,"volume":848},{"time":1773898440,"open":634,"high":636,"low":634,"close":636,"volume":862},{"time":1773898500,"open":636,"high":636,"low":632,"close":633,"volume":1239},{"time":1773898560,"open":633,"high":635,"low":632,"close":634,"volume":684},{"time":1773898620,"open":634,"high":634,"low":632,"close":633,"volume":516},{"time":1773898680,"open":633,"high":635,"low":632,"close":635,"volume":1078},{"time":1773898740,"open":635,"high":635,"low":634,"close":635,"volume":1092},{"time":1773898800,"open":635,"high":635,"low":634,"close":634,"volume":903},{"time":1773898860,"open":634,"high":636,"low":633,"close":635,"volume":1059},{"time":1773898920,"open":635,"high":635,"low":633,"close":633,"volume":1296},{"time":1773898980,"open":633,"high":634,"low":632,"close":634,"volume":631},{"time":1773899040,"open":634,"high":634,"low":634,"close":634,"volume":1092},{"time":1773899100,"open":634,"high":635,"low":633,"close":634,"volume":897},{"time":1773899160,"open":634,"high":635,"low":633,"close":635,"volume":532},{"time":1773899220,"open":635,"high":636,"low":633,"close":634,"volume":847},{"time":1773899280,"open":634,"high":636,"low":634,"close":634,"volume":1003},{"time":1773899340,"open":634,"high":636,"low":632,"close":633,"volume":911},{"time":1773899400,"open":633,"high":634,"low":632,"close":633,"volume":927},{"time":1773899460,"open":633,"high":634,"low":632,"close":633,"volume":987},{"time":1773899520,"open":633,"high":633,"low":632,"close":633,"volume":774},{"time":1773899580,"open":633,"high":634,"low":632,"close":634,"volume":1145},{"time":1773899640,"open":634,"high":635,"low":633,"close":633,"volume":1186},{"time":1773899700,"open":633,"high":636,"low":633,"close":635,"volume":1082},{"time":1773899760,"open":635,"high":635,"low":633,"close":634,"volume":775},{"time":1773899820,"open":634,"high":635,"low":633,"close":633,"volume":1055},{"time":1773899880,"open":633,"high":635,"low":633,"close":634,"volume":585},{"time":1773899940,"open":634,"high":635,"low":634,"close":634,"volume":843},{"time":1773900000,"open":634,"high":635,"low":633,"close":633,"volume":786},{"time":1773900060,"open":633,"high":634,"low":633,"close":633,"volume":883},{"time":1773900120,"open":633,"high":635,"low":632,"close":634,"volume":1117},{"time":1773900180,"open":634,"high":635,"low":632,"close":633,"volume":527},{"time":1773900240,"open":633,"high":634,"low":633,"close":634,"volume":979},{"time":1773900300,"open":634,"high":635,"low":633,"close":634,"volume":923},{"time":1773900360,"open":634,"high":634,"low":633,"close":634,"volume":1065},{"time":1773900420,"open":634,"high":634,"low":634,"close":634,"volume":652},{"time":1773900480,"open":634,"high":634,"low":633,"close":634,"volume":1072},{"time":1773900540,"open":634,"high":635,"low":632,"close":633,"volume":521},{"time":1773900600,"open":633,"high":634,"low":632,"close":634,"volume":881},{"time":1773900660,"open":634,"high":635,"low":633,"close":633,"volume":1018},{"time":1773900720,"open":633,"high":634,"low":632,"close":634,"volume":422},{"time":1773900780,"open":634,"high":635,"low":633,"close":634,"volume":426},{"time":1773900840,"open":634,"high":634,"low":633,"close":634,"volume":585},{"time":1773900900,"open":634,"high":634,"low":633,"close":633,"volume":724},{"time":1773900960,"open":633,"high":634,"low":633,"close":633,"volume":1108},{"time":1773901020,"open":633,"high":634,"low":633,"close":633,"volume":980},{"time":1773901080,"open":633,"high":634,"low":632,"close":632,"volume":1179},{"time":1773901140,"open":632,"high":634,"low":631,"close":633,"volume":654},{"time":1773901200,"open":633,"high":634,"low":633,"close":633,"volume":798},{"time":1773901260,"open":633,"high":634,"low":632,"close":633,"volume":903},{"time":1773901320,"open":633,"high":635,"low":633,"close":634,"volume":837},{"time":1773901380,"open":634,"high":634,"low":633,"close":633,"volume":663},{"time":1773901440,"open":633,"high":634,"low":633,"close":633,"volume":599},{"time":1773901500,"open":633,"high":634,"low":633,"close":633,"volume":534},{"time":1773901560,"open":633,"high":633,"low":632,"close":633,"volume":494},{"time":1773901620,"open":633,"high":634,"low":633,"close":633,"volume":836},{"time":1773901680,"open":633,"high":633,"low":633,"close":633,"volume":621},{"time":1773901740,"open":633,"high":634,"low":632,"close":633,"volume":1085}]}